package cn.com.fmsh.tsm.business.core;

import cn.com.fmsh.tsm.business.BusinessExtend;
import cn.com.fmsh.util.log.FMLog;
import cn.com.fmsh.util.log.LogFactory;

public class BusinessExtendImpl
  implements BusinessExtend
{
  public FMLog a = null;

  public BusinessExtendImpl(CardBusinessBasic paramCardBusinessBasic)
  {
    this.c = paramCardBusinessBasic;
    this.a = LogFactory.getInstance().getLog();
  }

  // ERROR //
  public int applyForElectronicTakeUp(byte[] paramArrayOfByte1, byte[] paramArrayOfByte2)
    throws cn.com.fmsh.tsm.business.exception.BusinessException
  {
    // Byte code:
    //   0: ldc 49
    //   2: sipush 186
    //   5: invokestatic 55	cn/com/fmsh/util/FM_Long:concat	(Ljava/lang/String;I)Ljava/lang/String;
    //   8: astore_3
    //   9: aload_0
    //   10: getfield 19	cn/com/fmsh/tsm/business/core/BusinessExtendImpl:a	Lcn/com/fmsh/util/log/FMLog;
    //   13: ifnonnull +13 -> 26
    //   16: aload_0
    //   17: invokestatic 37	cn/com/fmsh/util/log/LogFactory:getInstance	()Lcn/com/fmsh/util/log/LogFactory;
    //   20: invokevirtual 41	cn/com/fmsh/util/log/LogFactory:getLog	()Lcn/com/fmsh/util/log/FMLog;
    //   23: putfield 19	cn/com/fmsh/tsm/business/core/BusinessExtendImpl:a	Lcn/com/fmsh/util/log/FMLog;
    //   26: aload_0
    //   27: getfield 19	cn/com/fmsh/tsm/business/core/BusinessExtendImpl:a	Lcn/com/fmsh/util/log/FMLog;
    //   30: ifnull +24 -> 54
    //   33: aload_0
    //   34: getfield 19	cn/com/fmsh/tsm/business/core/BusinessExtendImpl:a	Lcn/com/fmsh/util/log/FMLog;
    //   37: aload_0
    //   38: getfield 29	cn/com/fmsh/tsm/business/core/BusinessExtendImpl:b	Ljava/lang/String;
    //   41: sipush 296
    //   44: ldc 57
    //   46: invokestatic 63	cn/com/fmsh/util/FM_Int:lastIndexOf	(ILjava/lang/String;)Ljava/lang/String;
    //   49: invokeinterface 69 3 0
    //   54: aload_0
    //   55: getfield 31	cn/com/fmsh/tsm/business/core/BusinessExtendImpl:c	Lcn/com/fmsh/tsm/business/core/CardBusinessBasic;
    //   58: ifnonnull +408 -> 466
    //   61: aload_0
    //   62: getfield 19	cn/com/fmsh/tsm/business/core/BusinessExtendImpl:a	Lcn/com/fmsh/util/log/FMLog;
    //   65: ifnull +41 -> 106
    //   68: aload_0
    //   69: getfield 19	cn/com/fmsh/tsm/business/core/BusinessExtendImpl:a	Lcn/com/fmsh/util/log/FMLog;
    //   72: aload_0
    //   73: getfield 29	cn/com/fmsh/tsm/business/core/BusinessExtendImpl:b	Ljava/lang/String;
    //   76: new 71	java/lang/StringBuilder
    //   79: dup
    //   80: aload_3
    //   81: invokestatic 77	java/lang/String:valueOf	(Ljava/lang/Object;)Ljava/lang/String;
    //   84: invokespecial 80	java/lang/StringBuilder:<init>	(Ljava/lang/String;)V
    //   87: iconst_5
    //   88: bipush 52
    //   90: ldc 82
    //   92: invokestatic 88	cn/com/fmsh/FM_Exception:getChars	(IILjava/lang/String;)Ljava/lang/String;
    //   95: invokevirtual 92	java/lang/StringBuilder:append	(Ljava/lang/String;)Ljava/lang/StringBuilder;
    //   98: invokevirtual 95	java/lang/StringBuilder:toString	()Ljava/lang/String;
    //   101: invokeinterface 98 3 0
    //   106: new 45	cn/com/fmsh/tsm/business/exception/BusinessException
    //   109: dup
    //   110: new 71	java/lang/StringBuilder
    //   113: dup
    //   114: aload_3
    //   115: invokestatic 77	java/lang/String:valueOf	(Ljava/lang/Object;)Ljava/lang/String;
    //   118: invokespecial 80	java/lang/StringBuilder:<init>	(Ljava/lang/String;)V
    //   121: ldc 100
    //   123: iconst_5
    //   124: bipush 57
    //   126: invokestatic 106	cn/com/fmsh/util/FM_Bytes:startsWith	(Ljava/lang/String;II)Ljava/lang/String;
    //   129: invokevirtual 92	java/lang/StringBuilder:append	(Ljava/lang/String;)Ljava/lang/StringBuilder;
    //   132: invokevirtual 95	java/lang/StringBuilder:toString	()Ljava/lang/String;
    //   135: getstatic 112	cn/com/fmsh/tsm/business/exception/BusinessException$ErrorMessage:local_business_init_fail	Lcn/com/fmsh/tsm/business/exception/BusinessException$ErrorMessage;
    //   138: invokespecial 115	cn/com/fmsh/tsm/business/exception/BusinessException:<init>	(Ljava/lang/String;Lcn/com/fmsh/tsm/business/exception/BusinessException$ErrorMessage;)V
    //   141: athrow
    //   142: aload_2
    //   143: ifnonnull +227 -> 370
    //   146: aload_0
    //   147: getfield 19	cn/com/fmsh/tsm/business/core/BusinessExtendImpl:a	Lcn/com/fmsh/util/log/FMLog;
    //   150: ifnull +43 -> 193
    //   153: aload_0
    //   154: getfield 19	cn/com/fmsh/tsm/business/core/BusinessExtendImpl:a	Lcn/com/fmsh/util/log/FMLog;
    //   157: aload_0
    //   158: getfield 29	cn/com/fmsh/tsm/business/core/BusinessExtendImpl:b	Ljava/lang/String;
    //   161: new 71	java/lang/StringBuilder
    //   164: dup
    //   165: aload_3
    //   166: invokestatic 77	java/lang/String:valueOf	(Ljava/lang/Object;)Ljava/lang/String;
    //   169: invokespecial 80	java/lang/StringBuilder:<init>	(Ljava/lang/String;)V
    //   172: sipush 214
    //   175: bipush 116
    //   177: ldc 117
    //   179: invokestatic 122	cn/com/fmsh/util/FM_Utils:copyValueOf	(IILjava/lang/String;)Ljava/lang/String;
    //   182: invokevirtual 92	java/lang/StringBuilder:append	(Ljava/lang/String;)Ljava/lang/StringBuilder;
    //   185: invokevirtual 95	java/lang/StringBuilder:toString	()Ljava/lang/String;
    //   188: invokeinterface 98 3 0
    //   193: new 45	cn/com/fmsh/tsm/business/exception/BusinessException
    //   196: dup
    //   197: new 71	java/lang/StringBuilder
    //   200: dup
    //   201: aload_3
    //   202: invokestatic 77	java/lang/String:valueOf	(Ljava/lang/Object;)Ljava/lang/String;
    //   205: invokespecial 80	java/lang/StringBuilder:<init>	(Ljava/lang/String;)V
    //   208: ldc 124
    //   210: bipush 124
    //   212: invokestatic 55	cn/com/fmsh/util/FM_Long:concat	(Ljava/lang/String;I)Ljava/lang/String;
    //   215: invokevirtual 92	java/lang/StringBuilder:append	(Ljava/lang/String;)Ljava/lang/StringBuilder;
    //   218: invokevirtual 95	java/lang/StringBuilder:toString	()Ljava/lang/String;
    //   221: getstatic 127	cn/com/fmsh/tsm/business/exception/BusinessException$ErrorMessage:local_message_load_config_fail	Lcn/com/fmsh/tsm/business/exception/BusinessException$ErrorMessage;
    //   224: invokespecial 115	cn/com/fmsh/tsm/business/exception/BusinessException:<init>	(Ljava/lang/String;Lcn/com/fmsh/tsm/business/exception/BusinessException$ErrorMessage;)V
    //   227: athrow
    //   228: aload_1
    //   229: ifnonnull -87 -> 142
    //   232: aload_0
    //   233: getfield 19	cn/com/fmsh/tsm/business/core/BusinessExtendImpl:a	Lcn/com/fmsh/util/log/FMLog;
    //   236: ifnull +43 -> 279
    //   239: aload_0
    //   240: getfield 19	cn/com/fmsh/tsm/business/core/BusinessExtendImpl:a	Lcn/com/fmsh/util/log/FMLog;
    //   243: aload_0
    //   244: getfield 29	cn/com/fmsh/tsm/business/core/BusinessExtendImpl:b	Ljava/lang/String;
    //   247: new 71	java/lang/StringBuilder
    //   250: dup
    //   251: aload_3
    //   252: invokestatic 77	java/lang/String:valueOf	(Ljava/lang/Object;)Ljava/lang/String;
    //   255: invokespecial 80	java/lang/StringBuilder:<init>	(Ljava/lang/String;)V
    //   258: sipush 190
    //   261: bipush 33
    //   263: ldc 129
    //   265: invokestatic 122	cn/com/fmsh/util/FM_Utils:copyValueOf	(IILjava/lang/String;)Ljava/lang/String;
    //   268: invokevirtual 92	java/lang/StringBuilder:append	(Ljava/lang/String;)Ljava/lang/StringBuilder;
    //   271: invokevirtual 95	java/lang/StringBuilder:toString	()Ljava/lang/String;
    //   274: invokeinterface 98 3 0
    //   279: new 45	cn/com/fmsh/tsm/business/exception/BusinessException
    //   282: dup
    //   283: new 71	java/lang/StringBuilder
    //   286: dup
    //   287: aload_3
    //   288: invokestatic 77	java/lang/String:valueOf	(Ljava/lang/Object;)Ljava/lang/String;
    //   291: invokespecial 80	java/lang/StringBuilder:<init>	(Ljava/lang/String;)V
    //   294: bipush 116
    //   296: bipush 13
    //   298: ldc 131
    //   300: invokestatic 122	cn/com/fmsh/util/FM_Utils:copyValueOf	(IILjava/lang/String;)Ljava/lang/String;
    //   303: invokevirtual 92	java/lang/StringBuilder:append	(Ljava/lang/String;)Ljava/lang/StringBuilder;
    //   306: invokevirtual 95	java/lang/StringBuilder:toString	()Ljava/lang/String;
    //   309: getstatic 127	cn/com/fmsh/tsm/business/exception/BusinessException$ErrorMessage:local_message_load_config_fail	Lcn/com/fmsh/tsm/business/exception/BusinessException$ErrorMessage;
    //   312: invokespecial 115	cn/com/fmsh/tsm/business/exception/BusinessException:<init>	(Ljava/lang/String;Lcn/com/fmsh/tsm/business/exception/BusinessException$ErrorMessage;)V
    //   315: athrow
    //   316: aload_0
    //   317: getfield 19	cn/com/fmsh/tsm/business/core/BusinessExtendImpl:a	Lcn/com/fmsh/util/log/FMLog;
    //   320: ifnull +40 -> 360
    //   323: aload_0
    //   324: getfield 19	cn/com/fmsh/tsm/business/core/BusinessExtendImpl:a	Lcn/com/fmsh/util/log/FMLog;
    //   327: aload_0
    //   328: getfield 29	cn/com/fmsh/tsm/business/core/BusinessExtendImpl:b	Ljava/lang/String;
    //   331: new 71	java/lang/StringBuilder
    //   334: dup
    //   335: iconst_2
    //   336: ldc 133
    //   338: invokestatic 137	cn/com/fmsh/util/CRCUtil:valueOf	(ILjava/lang/String;)Ljava/lang/String;
    //   341: invokespecial 80	java/lang/StringBuilder:<init>	(Ljava/lang/String;)V
    //   344: aload 15
    //   346: invokestatic 141	cn/com/fmsh/util/FM_Bytes:bytesToHexString	([B)Ljava/lang/String;
    //   349: invokevirtual 92	java/lang/StringBuilder:append	(Ljava/lang/String;)Ljava/lang/StringBuilder;
    //   352: invokevirtual 95	java/lang/StringBuilder:toString	()Ljava/lang/String;
    //   355: invokeinterface 98 3 0
    //   360: aload 16
    //   362: invokestatic 147	cn/com/fmsh/util/FM_CN:bcdBytesToInt	([B)I
    //   365: istore 17
    //   367: iload 17
    //   369: ireturn
    //   370: aload_0
    //   371: getfield 31	cn/com/fmsh/tsm/business/core/BusinessExtendImpl:c	Lcn/com/fmsh/tsm/business/core/CardBusinessBasic;
    //   374: sipush 1151
    //   377: invokevirtual 153	cn/com/fmsh/tsm/business/core/CardBusinessBasic:getServer4Business	(I)Ljava/lang/String;
    //   380: astore 5
    //   382: aload 5
    //   384: ifnonnull +315 -> 699
    //   387: aload_0
    //   388: getfield 19	cn/com/fmsh/tsm/business/core/BusinessExtendImpl:a	Lcn/com/fmsh/util/log/FMLog;
    //   391: ifnull +41 -> 432
    //   394: aload_0
    //   395: getfield 19	cn/com/fmsh/tsm/business/core/BusinessExtendImpl:a	Lcn/com/fmsh/util/log/FMLog;
    //   398: aload_0
    //   399: getfield 29	cn/com/fmsh/tsm/business/core/BusinessExtendImpl:b	Ljava/lang/String;
    //   402: new 71	java/lang/StringBuilder
    //   405: dup
    //   406: aload_3
    //   407: invokestatic 77	java/lang/String:valueOf	(Ljava/lang/Object;)Ljava/lang/String;
    //   410: invokespecial 80	java/lang/StringBuilder:<init>	(Ljava/lang/String;)V
    //   413: ldc 155
    //   415: iconst_5
    //   416: bipush 115
    //   418: invokestatic 160	cn/com/fmsh/util/BCCUtil:endsWith	(Ljava/lang/String;II)Ljava/lang/String;
    //   421: invokevirtual 92	java/lang/StringBuilder:append	(Ljava/lang/String;)Ljava/lang/StringBuilder;
    //   424: invokevirtual 95	java/lang/StringBuilder:toString	()Ljava/lang/String;
    //   427: invokeinterface 98 3 0
    //   432: new 45	cn/com/fmsh/tsm/business/exception/BusinessException
    //   435: dup
    //   436: new 71	java/lang/StringBuilder
    //   439: dup
    //   440: aload_3
    //   441: invokestatic 77	java/lang/String:valueOf	(Ljava/lang/Object;)Ljava/lang/String;
    //   444: invokespecial 80	java/lang/StringBuilder:<init>	(Ljava/lang/String;)V
    //   447: ldc 162
    //   449: iconst_5
    //   450: invokestatic 165	cn/com/fmsh/util/FM_CN:subSequence	(Ljava/lang/String;I)Ljava/lang/String;
    //   453: invokevirtual 92	java/lang/StringBuilder:append	(Ljava/lang/String;)Ljava/lang/StringBuilder;
    //   456: invokevirtual 95	java/lang/StringBuilder:toString	()Ljava/lang/String;
    //   459: getstatic 168	cn/com/fmsh/tsm/business/exception/BusinessException$ErrorMessage:local_app_query_server_fail	Lcn/com/fmsh/tsm/business/exception/BusinessException$ErrorMessage;
    //   462: invokespecial 115	cn/com/fmsh/tsm/business/exception/BusinessException:<init>	(Ljava/lang/String;Lcn/com/fmsh/tsm/business/exception/BusinessException$ErrorMessage;)V
    //   465: athrow
    //   466: aload_0
    //   467: getfield 31	cn/com/fmsh/tsm/business/core/BusinessExtendImpl:c	Lcn/com/fmsh/tsm/business/core/CardBusinessBasic;
    //   470: invokevirtual 172	cn/com/fmsh/tsm/business/core/CardBusinessBasic:getMessageHandler	()Lcn/com/fmsh/communication/message/IMessageHandler;
    //   473: astore 4
    //   475: aload 4
    //   477: ifnonnull -249 -> 228
    //   480: aload_0
    //   481: getfield 19	cn/com/fmsh/tsm/business/core/BusinessExtendImpl:a	Lcn/com/fmsh/util/log/FMLog;
    //   484: ifnull +39 -> 523
    //   487: aload_0
    //   488: getfield 19	cn/com/fmsh/tsm/business/core/BusinessExtendImpl:a	Lcn/com/fmsh/util/log/FMLog;
    //   491: aload_0
    //   492: getfield 29	cn/com/fmsh/tsm/business/core/BusinessExtendImpl:b	Ljava/lang/String;
    //   495: new 71	java/lang/StringBuilder
    //   498: dup
    //   499: aload_3
    //   500: invokestatic 77	java/lang/String:valueOf	(Ljava/lang/Object;)Ljava/lang/String;
    //   503: invokespecial 80	java/lang/StringBuilder:<init>	(Ljava/lang/String;)V
    //   506: ldc 174
    //   508: iconst_1
    //   509: invokestatic 165	cn/com/fmsh/util/FM_CN:subSequence	(Ljava/lang/String;I)Ljava/lang/String;
    //   512: invokevirtual 92	java/lang/StringBuilder:append	(Ljava/lang/String;)Ljava/lang/StringBuilder;
    //   515: invokevirtual 95	java/lang/StringBuilder:toString	()Ljava/lang/String;
    //   518: invokeinterface 98 3 0
    //   523: new 45	cn/com/fmsh/tsm/business/exception/BusinessException
    //   526: dup
    //   527: new 71	java/lang/StringBuilder
    //   530: dup
    //   531: aload_3
    //   532: invokestatic 77	java/lang/String:valueOf	(Ljava/lang/Object;)Ljava/lang/String;
    //   535: invokespecial 80	java/lang/StringBuilder:<init>	(Ljava/lang/String;)V
    //   538: ldc 176
    //   540: sipush 238
    //   543: invokestatic 55	cn/com/fmsh/util/FM_Long:concat	(Ljava/lang/String;I)Ljava/lang/String;
    //   546: invokevirtual 92	java/lang/StringBuilder:append	(Ljava/lang/String;)Ljava/lang/StringBuilder;
    //   549: invokevirtual 95	java/lang/StringBuilder:toString	()Ljava/lang/String;
    //   552: getstatic 127	cn/com/fmsh/tsm/business/exception/BusinessException$ErrorMessage:local_message_load_config_fail	Lcn/com/fmsh/tsm/business/exception/BusinessException$ErrorMessage;
    //   555: invokespecial 115	cn/com/fmsh/tsm/business/exception/BusinessException:<init>	(Ljava/lang/String;Lcn/com/fmsh/tsm/business/exception/BusinessException$ErrorMessage;)V
    //   558: athrow
    //   559: astore 18
    //   561: aload_0
    //   562: getfield 19	cn/com/fmsh/tsm/business/core/BusinessExtendImpl:a	Lcn/com/fmsh/util/log/FMLog;
    //   565: ifnull +47 -> 612
    //   568: aload_0
    //   569: getfield 19	cn/com/fmsh/tsm/business/core/BusinessExtendImpl:a	Lcn/com/fmsh/util/log/FMLog;
    //   572: aload_0
    //   573: getfield 29	cn/com/fmsh/tsm/business/core/BusinessExtendImpl:b	Ljava/lang/String;
    //   576: new 71	java/lang/StringBuilder
    //   579: dup
    //   580: aload_3
    //   581: invokestatic 77	java/lang/String:valueOf	(Ljava/lang/Object;)Ljava/lang/String;
    //   584: invokespecial 80	java/lang/StringBuilder:<init>	(Ljava/lang/String;)V
    //   587: ldc 178
    //   589: iconst_5
    //   590: invokestatic 55	cn/com/fmsh/util/FM_Long:concat	(Ljava/lang/String;I)Ljava/lang/String;
    //   593: invokevirtual 92	java/lang/StringBuilder:append	(Ljava/lang/String;)Ljava/lang/StringBuilder;
    //   596: aload 18
    //   598: invokestatic 184	cn/com/fmsh/util/Util4Java:getExceptionInfo	(Ljava/lang/Exception;)Ljava/lang/String;
    //   601: invokevirtual 92	java/lang/StringBuilder:append	(Ljava/lang/String;)Ljava/lang/StringBuilder;
    //   604: invokevirtual 95	java/lang/StringBuilder:toString	()Ljava/lang/String;
    //   607: invokeinterface 98 3 0
    //   612: aload_0
    //   613: getfield 31	cn/com/fmsh/tsm/business/core/BusinessExtendImpl:c	Lcn/com/fmsh/tsm/business/core/CardBusinessBasic;
    //   616: new 71	java/lang/StringBuilder
    //   619: dup
    //   620: aload_3
    //   621: invokestatic 77	java/lang/String:valueOf	(Ljava/lang/Object;)Ljava/lang/String;
    //   624: invokespecial 80	java/lang/StringBuilder:<init>	(Ljava/lang/String;)V
    //   627: sipush 296
    //   630: bipush 46
    //   632: ldc 186
    //   634: invokestatic 122	cn/com/fmsh/util/FM_Utils:copyValueOf	(IILjava/lang/String;)Ljava/lang/String;
    //   637: invokevirtual 92	java/lang/StringBuilder:append	(Ljava/lang/String;)Ljava/lang/StringBuilder;
    //   640: invokevirtual 95	java/lang/StringBuilder:toString	()Ljava/lang/String;
    //   643: getstatic 189	cn/com/fmsh/tsm/business/exception/BusinessException$ErrorMessage:local_message_message_handle_exception	Lcn/com/fmsh/tsm/business/exception/BusinessException$ErrorMessage;
    //   646: iconst_0
    //   647: invokevirtual 193	cn/com/fmsh/tsm/business/core/CardBusinessBasic:throwExceptionAndClose	(Ljava/lang/String;Lcn/com/fmsh/tsm/business/exception/BusinessException$ErrorMessage;Z)V
    //   650: aload_0
    //   651: getfield 31	cn/com/fmsh/tsm/business/core/BusinessExtendImpl:c	Lcn/com/fmsh/tsm/business/core/CardBusinessBasic;
    //   654: aload 6
    //   656: aload_3
    //   657: iconst_0
    //   658: aload 5
    //   660: invokevirtual 197	cn/com/fmsh/tsm/business/core/CardBusinessBasic:interaction	([BLjava/lang/String;ZLjava/lang/String;)[B
    //   663: astore 15
    //   665: iconst_2
    //   666: newarray byte
    //   668: astore 16
    //   670: aload 15
    //   672: iconst_0
    //   673: aload 16
    //   675: iconst_0
    //   676: aload 16
    //   678: arraylength
    //   679: invokestatic 203	java/lang/System:arraycopy	(Ljava/lang/Object;ILjava/lang/Object;II)V
    //   682: getstatic 209	cn/com/fmsh/tsm/business/constants/Constants$RespCodeonse4Platform:SUCESS	[B
    //   685: aload 16
    //   687: invokestatic 215	java/util/Arrays:equals	([B[B)Z
    //   690: ifeq -374 -> 316
    //   693: iconst_0
    //   694: istore 17
    //   696: goto -329 -> 367
    //   699: aload_0
    //   700: getfield 31	cn/com/fmsh/tsm/business/core/BusinessExtendImpl:c	Lcn/com/fmsh/tsm/business/core/CardBusinessBasic;
    //   703: aload_3
    //   704: aload 5
    //   706: invokevirtual 218	cn/com/fmsh/tsm/business/core/CardBusinessBasic:businessReady	(Ljava/lang/String;Ljava/lang/String;)V
    //   709: aconst_null
    //   710: astore 6
    //   712: aload 4
    //   714: sipush 4611
    //   717: invokeinterface 224 2 0
    //   722: astore 7
    //   724: aload 4
    //   726: bipush 112
    //   728: invokeinterface 228 2 0
    //   733: astore 8
    //   735: aload 8
    //   737: aload_1
    //   738: invokeinterface 233 2 0
    //   743: pop
    //   744: aload 7
    //   746: aload 8
    //   748: invokeinterface 239 2 0
    //   753: pop
    //   754: aload 4
    //   756: bipush 113
    //   758: invokeinterface 228 2 0
    //   763: astore 11
    //   765: aload 11
    //   767: aload_2
    //   768: invokeinterface 233 2 0
    //   773: pop
    //   774: aload 7
    //   776: aload 11
    //   778: invokeinterface 239 2 0
    //   783: pop
    //   784: aload 7
    //   786: invokeinterface 243 1 0
    //   791: astore 14
    //   793: aload 14
    //   795: astore 6
    //   797: goto -147 -> 650
    //
    // Exception table:
    //   from	to	target	type
    //   724	793	559	cn/com/fmsh/communication/message/exception/FMCommunicationMessageException
  }

  // ERROR //
  public cn.com.fmsh.tsm.business.bean.IdentifyingCode obtainIdentifyingCode(int paramInt, java.lang.String paramString)
    throws cn.com.fmsh.tsm.business.exception.BusinessException
  {
    // Byte code:
    //   0: sipush 188
    //   3: ldc 247
    //   5: invokestatic 63	cn/com/fmsh/util/FM_Int:lastIndexOf	(ILjava/lang/String;)Ljava/lang/String;
    //   8: astore_3
    //   9: aload_0
    //   10: getfield 19	cn/com/fmsh/tsm/business/core/BusinessExtendImpl:a	Lcn/com/fmsh/util/log/FMLog;
    //   13: ifnonnull +13 -> 26
    //   16: aload_0
    //   17: invokestatic 37	cn/com/fmsh/util/log/LogFactory:getInstance	()Lcn/com/fmsh/util/log/LogFactory;
    //   20: invokevirtual 41	cn/com/fmsh/util/log/LogFactory:getLog	()Lcn/com/fmsh/util/log/FMLog;
    //   23: putfield 19	cn/com/fmsh/tsm/business/core/BusinessExtendImpl:a	Lcn/com/fmsh/util/log/FMLog;
    //   26: aload_0
    //   27: getfield 19	cn/com/fmsh/tsm/business/core/BusinessExtendImpl:a	Lcn/com/fmsh/util/log/FMLog;
    //   30: ifnull +24 -> 54
    //   33: aload_0
    //   34: getfield 19	cn/com/fmsh/tsm/business/core/BusinessExtendImpl:a	Lcn/com/fmsh/util/log/FMLog;
    //   37: aload_0
    //   38: getfield 29	cn/com/fmsh/tsm/business/core/BusinessExtendImpl:b	Ljava/lang/String;
    //   41: iconst_2
    //   42: bipush 25
    //   44: ldc 249
    //   46: invokestatic 122	cn/com/fmsh/util/FM_Utils:copyValueOf	(IILjava/lang/String;)Ljava/lang/String;
    //   49: invokeinterface 69 3 0
    //   54: iload_1
    //   55: ifge +688 -> 743
    //   58: aload_0
    //   59: getfield 19	cn/com/fmsh/tsm/business/core/BusinessExtendImpl:a	Lcn/com/fmsh/util/log/FMLog;
    //   62: ifnull +41 -> 103
    //   65: aload_0
    //   66: getfield 19	cn/com/fmsh/tsm/business/core/BusinessExtendImpl:a	Lcn/com/fmsh/util/log/FMLog;
    //   69: aload_0
    //   70: getfield 29	cn/com/fmsh/tsm/business/core/BusinessExtendImpl:b	Ljava/lang/String;
    //   73: new 71	java/lang/StringBuilder
    //   76: dup
    //   77: aload_3
    //   78: invokestatic 77	java/lang/String:valueOf	(Ljava/lang/Object;)Ljava/lang/String;
    //   81: invokespecial 80	java/lang/StringBuilder:<init>	(Ljava/lang/String;)V
    //   84: ldc 251
    //   86: iconst_3
    //   87: bipush 67
    //   89: invokestatic 106	cn/com/fmsh/util/FM_Bytes:startsWith	(Ljava/lang/String;II)Ljava/lang/String;
    //   92: invokevirtual 92	java/lang/StringBuilder:append	(Ljava/lang/String;)Ljava/lang/StringBuilder;
    //   95: invokevirtual 95	java/lang/StringBuilder:toString	()Ljava/lang/String;
    //   98: invokeinterface 98 3 0
    //   103: new 45	cn/com/fmsh/tsm/business/exception/BusinessException
    //   106: dup
    //   107: new 71	java/lang/StringBuilder
    //   110: dup
    //   111: aload_3
    //   112: invokestatic 77	java/lang/String:valueOf	(Ljava/lang/Object;)Ljava/lang/String;
    //   115: invokespecial 80	java/lang/StringBuilder:<init>	(Ljava/lang/String;)V
    //   118: iconst_2
    //   119: bipush 87
    //   121: ldc 253
    //   123: invokestatic 122	cn/com/fmsh/util/FM_Utils:copyValueOf	(IILjava/lang/String;)Ljava/lang/String;
    //   126: invokevirtual 92	java/lang/StringBuilder:append	(Ljava/lang/String;)Ljava/lang/StringBuilder;
    //   129: invokevirtual 95	java/lang/StringBuilder:toString	()Ljava/lang/String;
    //   132: getstatic 127	cn/com/fmsh/tsm/business/exception/BusinessException$ErrorMessage:local_message_load_config_fail	Lcn/com/fmsh/tsm/business/exception/BusinessException$ErrorMessage;
    //   135: invokespecial 115	cn/com/fmsh/tsm/business/exception/BusinessException:<init>	(Ljava/lang/String;Lcn/com/fmsh/tsm/business/exception/BusinessException$ErrorMessage;)V
    //   138: athrow
    //   139: astore 18
    //   141: aload_0
    //   142: getfield 19	cn/com/fmsh/tsm/business/core/BusinessExtendImpl:a	Lcn/com/fmsh/util/log/FMLog;
    //   145: ifnull +51 -> 196
    //   148: aload_0
    //   149: getfield 19	cn/com/fmsh/tsm/business/core/BusinessExtendImpl:a	Lcn/com/fmsh/util/log/FMLog;
    //   152: aload_0
    //   153: getfield 29	cn/com/fmsh/tsm/business/core/BusinessExtendImpl:b	Ljava/lang/String;
    //   156: new 71	java/lang/StringBuilder
    //   159: dup
    //   160: aload_3
    //   161: invokestatic 77	java/lang/String:valueOf	(Ljava/lang/Object;)Ljava/lang/String;
    //   164: invokespecial 80	java/lang/StringBuilder:<init>	(Ljava/lang/String;)V
    //   167: ldc 255
    //   169: sipush 182
    //   172: bipush 99
    //   174: invokestatic 106	cn/com/fmsh/util/FM_Bytes:startsWith	(Ljava/lang/String;II)Ljava/lang/String;
    //   177: invokevirtual 92	java/lang/StringBuilder:append	(Ljava/lang/String;)Ljava/lang/StringBuilder;
    //   180: aload 18
    //   182: invokestatic 184	cn/com/fmsh/util/Util4Java:getExceptionInfo	(Ljava/lang/Exception;)Ljava/lang/String;
    //   185: invokevirtual 92	java/lang/StringBuilder:append	(Ljava/lang/String;)Ljava/lang/StringBuilder;
    //   188: invokevirtual 95	java/lang/StringBuilder:toString	()Ljava/lang/String;
    //   191: invokeinterface 98 3 0
    //   196: aload_0
    //   197: getfield 31	cn/com/fmsh/tsm/business/core/BusinessExtendImpl:c	Lcn/com/fmsh/tsm/business/core/CardBusinessBasic;
    //   200: new 71	java/lang/StringBuilder
    //   203: dup
    //   204: aload_3
    //   205: invokestatic 77	java/lang/String:valueOf	(Ljava/lang/Object;)Ljava/lang/String;
    //   208: invokespecial 80	java/lang/StringBuilder:<init>	(Ljava/lang/String;)V
    //   211: ldc_w 257
    //   214: iconst_1
    //   215: invokestatic 165	cn/com/fmsh/util/FM_CN:subSequence	(Ljava/lang/String;I)Ljava/lang/String;
    //   218: invokevirtual 92	java/lang/StringBuilder:append	(Ljava/lang/String;)Ljava/lang/StringBuilder;
    //   221: invokevirtual 95	java/lang/StringBuilder:toString	()Ljava/lang/String;
    //   224: getstatic 189	cn/com/fmsh/tsm/business/exception/BusinessException$ErrorMessage:local_message_message_handle_exception	Lcn/com/fmsh/tsm/business/exception/BusinessException$ErrorMessage;
    //   227: iconst_0
    //   228: invokevirtual 193	cn/com/fmsh/tsm/business/core/CardBusinessBasic:throwExceptionAndClose	(Ljava/lang/String;Lcn/com/fmsh/tsm/business/exception/BusinessException$ErrorMessage;Z)V
    //   231: aload_0
    //   232: getfield 31	cn/com/fmsh/tsm/business/core/BusinessExtendImpl:c	Lcn/com/fmsh/tsm/business/core/CardBusinessBasic;
    //   235: aload 6
    //   237: aload_3
    //   238: iconst_0
    //   239: aload 5
    //   241: invokevirtual 197	cn/com/fmsh/tsm/business/core/CardBusinessBasic:interaction	([BLjava/lang/String;ZLjava/lang/String;)[B
    //   244: astore 12
    //   246: getstatic 209	cn/com/fmsh/tsm/business/constants/Constants$RespCodeonse4Platform:SUCESS	[B
    //   249: aload 12
    //   251: iconst_2
    //   252: invokestatic 261	java/util/Arrays:copyOf	([BI)[B
    //   255: invokestatic 215	java/util/Arrays:equals	([B[B)Z
    //   258: ifne +96 -> 354
    //   261: aload_0
    //   262: getfield 19	cn/com/fmsh/tsm/business/core/BusinessExtendImpl:a	Lcn/com/fmsh/util/log/FMLog;
    //   265: ifnull +52 -> 317
    //   268: aload_0
    //   269: getfield 19	cn/com/fmsh/tsm/business/core/BusinessExtendImpl:a	Lcn/com/fmsh/util/log/FMLog;
    //   272: aload_0
    //   273: getfield 29	cn/com/fmsh/tsm/business/core/BusinessExtendImpl:b	Ljava/lang/String;
    //   276: new 71	java/lang/StringBuilder
    //   279: dup
    //   280: aload_3
    //   281: invokestatic 77	java/lang/String:valueOf	(Ljava/lang/Object;)Ljava/lang/String;
    //   284: invokespecial 80	java/lang/StringBuilder:<init>	(Ljava/lang/String;)V
    //   287: sipush 342
    //   290: bipush 88
    //   292: ldc_w 263
    //   295: invokestatic 122	cn/com/fmsh/util/FM_Utils:copyValueOf	(IILjava/lang/String;)Ljava/lang/String;
    //   298: invokevirtual 92	java/lang/StringBuilder:append	(Ljava/lang/String;)Ljava/lang/StringBuilder;
    //   301: aload 12
    //   303: invokestatic 141	cn/com/fmsh/util/FM_Bytes:bytesToHexString	([B)Ljava/lang/String;
    //   306: invokevirtual 92	java/lang/StringBuilder:append	(Ljava/lang/String;)Ljava/lang/StringBuilder;
    //   309: invokevirtual 95	java/lang/StringBuilder:toString	()Ljava/lang/String;
    //   312: invokeinterface 266 3 0
    //   317: aload_0
    //   318: getfield 31	cn/com/fmsh/tsm/business/core/BusinessExtendImpl:c	Lcn/com/fmsh/tsm/business/core/CardBusinessBasic;
    //   321: new 71	java/lang/StringBuilder
    //   324: dup
    //   325: aload_3
    //   326: invokestatic 77	java/lang/String:valueOf	(Ljava/lang/Object;)Ljava/lang/String;
    //   329: invokespecial 80	java/lang/StringBuilder:<init>	(Ljava/lang/String;)V
    //   332: ldc_w 268
    //   335: iconst_5
    //   336: bipush 39
    //   338: invokestatic 106	cn/com/fmsh/util/FM_Bytes:startsWith	(Ljava/lang/String;II)Ljava/lang/String;
    //   341: invokevirtual 92	java/lang/StringBuilder:append	(Ljava/lang/String;)Ljava/lang/StringBuilder;
    //   344: invokevirtual 95	java/lang/StringBuilder:toString	()Ljava/lang/String;
    //   347: getstatic 271	cn/com/fmsh/tsm/business/exception/BusinessException$ErrorMessage:local_message_platform_business_handle_fail	Lcn/com/fmsh/tsm/business/exception/BusinessException$ErrorMessage;
    //   350: iconst_1
    //   351: invokevirtual 193	cn/com/fmsh/tsm/business/core/CardBusinessBasic:throwExceptionAndClose	(Ljava/lang/String;Lcn/com/fmsh/tsm/business/exception/BusinessException$ErrorMessage;Z)V
    //   354: new 273	cn/com/fmsh/tsm/business/bean/IdentifyingCode
    //   357: dup
    //   358: invokespecial 274	cn/com/fmsh/tsm/business/bean/IdentifyingCode:<init>	()V
    //   361: astore 13
    //   363: aload 4
    //   365: sipush 4631
    //   368: aload 12
    //   370: iconst_2
    //   371: aload 12
    //   373: arraylength
    //   374: invokestatic 278	java/util/Arrays:copyOfRange	([BII)[B
    //   377: invokeinterface 281 3 0
    //   382: astore 15
    //   384: aload 15
    //   386: bipush 11
    //   388: invokeinterface 285 2 0
    //   393: astore 16
    //   395: aload 16
    //   397: ifnull +15 -> 412
    //   400: aload 13
    //   402: aload 16
    //   404: invokeinterface 288 1 0
    //   409: invokevirtual 291	cn/com/fmsh/tsm/business/bean/IdentifyingCode:setCode	(Ljava/lang/String;)V
    //   412: aload 15
    //   414: bipush 64
    //   416: invokeinterface 285 2 0
    //   421: astore 17
    //   423: aload 17
    //   425: ifnull +15 -> 440
    //   428: aload 13
    //   430: aload 17
    //   432: invokeinterface 288 1 0
    //   437: invokevirtual 294	cn/com/fmsh/tsm/business/bean/IdentifyingCode:setSerial	(Ljava/lang/String;)V
    //   440: aload 13
    //   442: areturn
    //   443: aload_0
    //   444: getfield 31	cn/com/fmsh/tsm/business/core/BusinessExtendImpl:c	Lcn/com/fmsh/tsm/business/core/CardBusinessBasic;
    //   447: sipush 1151
    //   450: invokevirtual 153	cn/com/fmsh/tsm/business/core/CardBusinessBasic:getServer4Business	(I)Ljava/lang/String;
    //   453: astore 5
    //   455: aload 5
    //   457: ifnonnull +182 -> 639
    //   460: aload_0
    //   461: getfield 19	cn/com/fmsh/tsm/business/core/BusinessExtendImpl:a	Lcn/com/fmsh/util/log/FMLog;
    //   464: ifnull +42 -> 506
    //   467: aload_0
    //   468: getfield 19	cn/com/fmsh/tsm/business/core/BusinessExtendImpl:a	Lcn/com/fmsh/util/log/FMLog;
    //   471: aload_0
    //   472: getfield 29	cn/com/fmsh/tsm/business/core/BusinessExtendImpl:b	Ljava/lang/String;
    //   475: new 71	java/lang/StringBuilder
    //   478: dup
    //   479: aload_3
    //   480: invokestatic 77	java/lang/String:valueOf	(Ljava/lang/Object;)Ljava/lang/String;
    //   483: invokespecial 80	java/lang/StringBuilder:<init>	(Ljava/lang/String;)V
    //   486: sipush 314
    //   489: ldc_w 296
    //   492: invokestatic 137	cn/com/fmsh/util/CRCUtil:valueOf	(ILjava/lang/String;)Ljava/lang/String;
    //   495: invokevirtual 92	java/lang/StringBuilder:append	(Ljava/lang/String;)Ljava/lang/StringBuilder;
    //   498: invokevirtual 95	java/lang/StringBuilder:toString	()Ljava/lang/String;
    //   501: invokeinterface 98 3 0
    //   506: new 45	cn/com/fmsh/tsm/business/exception/BusinessException
    //   509: dup
    //   510: new 71	java/lang/StringBuilder
    //   513: dup
    //   514: aload_3
    //   515: invokestatic 77	java/lang/String:valueOf	(Ljava/lang/Object;)Ljava/lang/String;
    //   518: invokespecial 80	java/lang/StringBuilder:<init>	(Ljava/lang/String;)V
    //   521: ldc_w 298
    //   524: sipush 238
    //   527: invokestatic 165	cn/com/fmsh/util/FM_CN:subSequence	(Ljava/lang/String;I)Ljava/lang/String;
    //   530: invokevirtual 92	java/lang/StringBuilder:append	(Ljava/lang/String;)Ljava/lang/StringBuilder;
    //   533: invokevirtual 95	java/lang/StringBuilder:toString	()Ljava/lang/String;
    //   536: getstatic 168	cn/com/fmsh/tsm/business/exception/BusinessException$ErrorMessage:local_app_query_server_fail	Lcn/com/fmsh/tsm/business/exception/BusinessException$ErrorMessage;
    //   539: invokespecial 115	cn/com/fmsh/tsm/business/exception/BusinessException:<init>	(Ljava/lang/String;Lcn/com/fmsh/tsm/business/exception/BusinessException$ErrorMessage;)V
    //   542: athrow
    //   543: aload_0
    //   544: getfield 31	cn/com/fmsh/tsm/business/core/BusinessExtendImpl:c	Lcn/com/fmsh/tsm/business/core/CardBusinessBasic;
    //   547: invokevirtual 172	cn/com/fmsh/tsm/business/core/CardBusinessBasic:getMessageHandler	()Lcn/com/fmsh/communication/message/IMessageHandler;
    //   550: astore 4
    //   552: aload 4
    //   554: ifnonnull -111 -> 443
    //   557: aload_0
    //   558: getfield 19	cn/com/fmsh/tsm/business/core/BusinessExtendImpl:a	Lcn/com/fmsh/util/log/FMLog;
    //   561: ifnull +43 -> 604
    //   564: aload_0
    //   565: getfield 19	cn/com/fmsh/tsm/business/core/BusinessExtendImpl:a	Lcn/com/fmsh/util/log/FMLog;
    //   568: aload_0
    //   569: getfield 29	cn/com/fmsh/tsm/business/core/BusinessExtendImpl:b	Ljava/lang/String;
    //   572: new 71	java/lang/StringBuilder
    //   575: dup
    //   576: aload_3
    //   577: invokestatic 77	java/lang/String:valueOf	(Ljava/lang/Object;)Ljava/lang/String;
    //   580: invokespecial 80	java/lang/StringBuilder:<init>	(Ljava/lang/String;)V
    //   583: ldc_w 300
    //   586: bipush 120
    //   588: bipush 77
    //   590: invokestatic 106	cn/com/fmsh/util/FM_Bytes:startsWith	(Ljava/lang/String;II)Ljava/lang/String;
    //   593: invokevirtual 92	java/lang/StringBuilder:append	(Ljava/lang/String;)Ljava/lang/StringBuilder;
    //   596: invokevirtual 95	java/lang/StringBuilder:toString	()Ljava/lang/String;
    //   599: invokeinterface 98 3 0
    //   604: new 45	cn/com/fmsh/tsm/business/exception/BusinessException
    //   607: dup
    //   608: new 71	java/lang/StringBuilder
    //   611: dup
    //   612: aload_3
    //   613: invokestatic 77	java/lang/String:valueOf	(Ljava/lang/Object;)Ljava/lang/String;
    //   616: invokespecial 80	java/lang/StringBuilder:<init>	(Ljava/lang/String;)V
    //   619: iconst_1
    //   620: ldc_w 302
    //   623: invokestatic 63	cn/com/fmsh/util/FM_Int:lastIndexOf	(ILjava/lang/String;)Ljava/lang/String;
    //   626: invokevirtual 92	java/lang/StringBuilder:append	(Ljava/lang/String;)Ljava/lang/StringBuilder;
    //   629: invokevirtual 95	java/lang/StringBuilder:toString	()Ljava/lang/String;
    //   632: getstatic 127	cn/com/fmsh/tsm/business/exception/BusinessException$ErrorMessage:local_message_load_config_fail	Lcn/com/fmsh/tsm/business/exception/BusinessException$ErrorMessage;
    //   635: invokespecial 115	cn/com/fmsh/tsm/business/exception/BusinessException:<init>	(Ljava/lang/String;Lcn/com/fmsh/tsm/business/exception/BusinessException$ErrorMessage;)V
    //   638: athrow
    //   639: aload_0
    //   640: getfield 31	cn/com/fmsh/tsm/business/core/BusinessExtendImpl:c	Lcn/com/fmsh/tsm/business/core/CardBusinessBasic;
    //   643: aload_3
    //   644: aload 5
    //   646: invokevirtual 218	cn/com/fmsh/tsm/business/core/CardBusinessBasic:businessReady	(Ljava/lang/String;Ljava/lang/String;)V
    //   649: aconst_null
    //   650: astore 6
    //   652: aload 4
    //   654: sipush 1061
    //   657: invokeinterface 224 2 0
    //   662: astore 7
    //   664: aload_2
    //   665: ifnull +32 -> 697
    //   668: aload 4
    //   670: iconst_5
    //   671: invokeinterface 228 2 0
    //   676: astore 19
    //   678: aload 19
    //   680: aload_2
    //   681: invokeinterface 305 2 0
    //   686: pop
    //   687: aload 7
    //   689: aload 19
    //   691: invokeinterface 239 2 0
    //   696: pop
    //   697: aload 4
    //   699: bipush 11
    //   701: invokeinterface 228 2 0
    //   706: astore 8
    //   708: aload 8
    //   710: iload_1
    //   711: invokeinterface 308 2 0
    //   716: pop
    //   717: aload 7
    //   719: aload 8
    //   721: invokeinterface 239 2 0
    //   726: pop
    //   727: aload 7
    //   729: invokeinterface 243 1 0
    //   734: astore 11
    //   736: aload 11
    //   738: astore 6
    //   740: goto -509 -> 231
    //   743: aload_0
    //   744: getfield 31	cn/com/fmsh/tsm/business/core/BusinessExtendImpl:c	Lcn/com/fmsh/tsm/business/core/CardBusinessBasic;
    //   747: ifnonnull -204 -> 543
    //   750: aload_0
    //   751: getfield 19	cn/com/fmsh/tsm/business/core/BusinessExtendImpl:a	Lcn/com/fmsh/util/log/FMLog;
    //   754: ifnull +41 -> 795
    //   757: aload_0
    //   758: getfield 19	cn/com/fmsh/tsm/business/core/BusinessExtendImpl:a	Lcn/com/fmsh/util/log/FMLog;
    //   761: aload_0
    //   762: getfield 29	cn/com/fmsh/tsm/business/core/BusinessExtendImpl:b	Ljava/lang/String;
    //   765: new 71	java/lang/StringBuilder
    //   768: dup
    //   769: aload_3
    //   770: invokestatic 77	java/lang/String:valueOf	(Ljava/lang/Object;)Ljava/lang/String;
    //   773: invokespecial 80	java/lang/StringBuilder:<init>	(Ljava/lang/String;)V
    //   776: ldc_w 310
    //   779: bipush 98
    //   781: invokestatic 55	cn/com/fmsh/util/FM_Long:concat	(Ljava/lang/String;I)Ljava/lang/String;
    //   784: invokevirtual 92	java/lang/StringBuilder:append	(Ljava/lang/String;)Ljava/lang/StringBuilder;
    //   787: invokevirtual 95	java/lang/StringBuilder:toString	()Ljava/lang/String;
    //   790: invokeinterface 98 3 0
    //   795: new 45	cn/com/fmsh/tsm/business/exception/BusinessException
    //   798: dup
    //   799: new 71	java/lang/StringBuilder
    //   802: dup
    //   803: aload_3
    //   804: invokestatic 77	java/lang/String:valueOf	(Ljava/lang/Object;)Ljava/lang/String;
    //   807: invokespecial 80	java/lang/StringBuilder:<init>	(Ljava/lang/String;)V
    //   810: iconst_5
    //   811: ldc_w 312
    //   814: invokestatic 137	cn/com/fmsh/util/CRCUtil:valueOf	(ILjava/lang/String;)Ljava/lang/String;
    //   817: invokevirtual 92	java/lang/StringBuilder:append	(Ljava/lang/String;)Ljava/lang/StringBuilder;
    //   820: invokevirtual 95	java/lang/StringBuilder:toString	()Ljava/lang/String;
    //   823: getstatic 112	cn/com/fmsh/tsm/business/exception/BusinessException$ErrorMessage:local_business_init_fail	Lcn/com/fmsh/tsm/business/exception/BusinessException$ErrorMessage;
    //   826: invokespecial 115	cn/com/fmsh/tsm/business/exception/BusinessException:<init>	(Ljava/lang/String;Lcn/com/fmsh/tsm/business/exception/BusinessException$ErrorMessage;)V
    //   829: athrow
    //   830: astore 14
    //   832: aload_0
    //   833: getfield 19	cn/com/fmsh/tsm/business/core/BusinessExtendImpl:a	Lcn/com/fmsh/util/log/FMLog;
    //   836: ifnull +50 -> 886
    //   839: aload_0
    //   840: getfield 19	cn/com/fmsh/tsm/business/core/BusinessExtendImpl:a	Lcn/com/fmsh/util/log/FMLog;
    //   843: aload_0
    //   844: getfield 29	cn/com/fmsh/tsm/business/core/BusinessExtendImpl:b	Ljava/lang/String;
    //   847: new 71	java/lang/StringBuilder
    //   850: dup
    //   851: aload_3
    //   852: invokestatic 77	java/lang/String:valueOf	(Ljava/lang/Object;)Ljava/lang/String;
    //   855: invokespecial 80	java/lang/StringBuilder:<init>	(Ljava/lang/String;)V
    //   858: ldc_w 314
    //   861: iconst_4
    //   862: bipush 109
    //   864: invokestatic 316	cn/com/fmsh/util/Util4Java:toString	(Ljava/lang/String;II)Ljava/lang/String;
    //   867: invokevirtual 92	java/lang/StringBuilder:append	(Ljava/lang/String;)Ljava/lang/StringBuilder;
    //   870: aload 12
    //   872: invokestatic 141	cn/com/fmsh/util/FM_Bytes:bytesToHexString	([B)Ljava/lang/String;
    //   875: invokevirtual 92	java/lang/StringBuilder:append	(Ljava/lang/String;)Ljava/lang/StringBuilder;
    //   878: invokevirtual 95	java/lang/StringBuilder:toString	()Ljava/lang/String;
    //   881: invokeinterface 98 3 0
    //   886: aload_0
    //   887: getfield 31	cn/com/fmsh/tsm/business/core/BusinessExtendImpl:c	Lcn/com/fmsh/tsm/business/core/CardBusinessBasic;
    //   890: new 71	java/lang/StringBuilder
    //   893: dup
    //   894: aload_3
    //   895: invokestatic 77	java/lang/String:valueOf	(Ljava/lang/Object;)Ljava/lang/String;
    //   898: invokespecial 80	java/lang/StringBuilder:<init>	(Ljava/lang/String;)V
    //   901: iconst_3
    //   902: bipush 83
    //   904: ldc_w 318
    //   907: invokestatic 88	cn/com/fmsh/FM_Exception:getChars	(IILjava/lang/String;)Ljava/lang/String;
    //   910: invokevirtual 92	java/lang/StringBuilder:append	(Ljava/lang/String;)Ljava/lang/StringBuilder;
    //   913: invokevirtual 95	java/lang/StringBuilder:toString	()Ljava/lang/String;
    //   916: getstatic 321	cn/com/fmsh/tsm/business/exception/BusinessException$ErrorMessage:local_message_command_data_invaild	Lcn/com/fmsh/tsm/business/exception/BusinessException$ErrorMessage;
    //   919: iconst_0
    //   920: invokevirtual 193	cn/com/fmsh/tsm/business/core/CardBusinessBasic:throwExceptionAndClose	(Ljava/lang/String;Lcn/com/fmsh/tsm/business/exception/BusinessException$ErrorMessage;Z)V
    //   923: goto -483 -> 440
    //
    // Exception table:
    //   from	to	target	type
    //   668	736	139	cn/com/fmsh/communication/message/exception/FMCommunicationMessageException
    //   363	440	830	cn/com/fmsh/communication/message/exception/FMCommunicationMessageException
  }

  // ERROR //
  public cn.com.fmsh.tsm.business.bean.ElectronicTakeUp queryElectronicTakeUp(byte[] paramArrayOfByte1, byte[] paramArrayOfByte2)
    throws cn.com.fmsh.tsm.business.exception.BusinessException
  {
    // Byte code:
    //   0: sipush 232
    //   3: ldc_w 325
    //   6: invokestatic 137	cn/com/fmsh/util/CRCUtil:valueOf	(ILjava/lang/String;)Ljava/lang/String;
    //   9: astore_3
    //   10: aload_0
    //   11: getfield 19	cn/com/fmsh/tsm/business/core/BusinessExtendImpl:a	Lcn/com/fmsh/util/log/FMLog;
    //   14: ifnonnull +13 -> 27
    //   17: aload_0
    //   18: invokestatic 37	cn/com/fmsh/util/log/LogFactory:getInstance	()Lcn/com/fmsh/util/log/LogFactory;
    //   21: invokevirtual 41	cn/com/fmsh/util/log/LogFactory:getLog	()Lcn/com/fmsh/util/log/FMLog;
    //   24: putfield 19	cn/com/fmsh/tsm/business/core/BusinessExtendImpl:a	Lcn/com/fmsh/util/log/FMLog;
    //   27: aload_0
    //   28: getfield 19	cn/com/fmsh/tsm/business/core/BusinessExtendImpl:a	Lcn/com/fmsh/util/log/FMLog;
    //   31: ifnull +25 -> 56
    //   34: aload_0
    //   35: getfield 19	cn/com/fmsh/tsm/business/core/BusinessExtendImpl:a	Lcn/com/fmsh/util/log/FMLog;
    //   38: aload_0
    //   39: getfield 29	cn/com/fmsh/tsm/business/core/BusinessExtendImpl:b	Ljava/lang/String;
    //   42: ldc_w 327
    //   45: iconst_2
    //   46: bipush 90
    //   48: invokestatic 160	cn/com/fmsh/util/BCCUtil:endsWith	(Ljava/lang/String;II)Ljava/lang/String;
    //   51: invokeinterface 69 3 0
    //   56: aload_0
    //   57: getfield 31	cn/com/fmsh/tsm/business/core/BusinessExtendImpl:c	Lcn/com/fmsh/tsm/business/core/CardBusinessBasic;
    //   60: ifnonnull +373 -> 433
    //   63: aload_0
    //   64: getfield 19	cn/com/fmsh/tsm/business/core/BusinessExtendImpl:a	Lcn/com/fmsh/util/log/FMLog;
    //   67: ifnull +42 -> 109
    //   70: aload_0
    //   71: getfield 19	cn/com/fmsh/tsm/business/core/BusinessExtendImpl:a	Lcn/com/fmsh/util/log/FMLog;
    //   74: aload_0
    //   75: getfield 29	cn/com/fmsh/tsm/business/core/BusinessExtendImpl:b	Ljava/lang/String;
    //   78: new 71	java/lang/StringBuilder
    //   81: dup
    //   82: aload_3
    //   83: invokestatic 77	java/lang/String:valueOf	(Ljava/lang/Object;)Ljava/lang/String;
    //   86: invokespecial 80	java/lang/StringBuilder:<init>	(Ljava/lang/String;)V
    //   89: sipush 194
    //   92: ldc_w 329
    //   95: invokestatic 137	cn/com/fmsh/util/CRCUtil:valueOf	(ILjava/lang/String;)Ljava/lang/String;
    //   98: invokevirtual 92	java/lang/StringBuilder:append	(Ljava/lang/String;)Ljava/lang/StringBuilder;
    //   101: invokevirtual 95	java/lang/StringBuilder:toString	()Ljava/lang/String;
    //   104: invokeinterface 98 3 0
    //   109: new 45	cn/com/fmsh/tsm/business/exception/BusinessException
    //   112: dup
    //   113: new 71	java/lang/StringBuilder
    //   116: dup
    //   117: aload_3
    //   118: invokestatic 77	java/lang/String:valueOf	(Ljava/lang/Object;)Ljava/lang/String;
    //   121: invokespecial 80	java/lang/StringBuilder:<init>	(Ljava/lang/String;)V
    //   124: ldc_w 331
    //   127: sipush 200
    //   130: bipush 113
    //   132: invokestatic 316	cn/com/fmsh/util/Util4Java:toString	(Ljava/lang/String;II)Ljava/lang/String;
    //   135: invokevirtual 92	java/lang/StringBuilder:append	(Ljava/lang/String;)Ljava/lang/StringBuilder;
    //   138: invokevirtual 95	java/lang/StringBuilder:toString	()Ljava/lang/String;
    //   141: getstatic 112	cn/com/fmsh/tsm/business/exception/BusinessException$ErrorMessage:local_business_init_fail	Lcn/com/fmsh/tsm/business/exception/BusinessException$ErrorMessage;
    //   144: invokespecial 115	cn/com/fmsh/tsm/business/exception/BusinessException:<init>	(Ljava/lang/String;Lcn/com/fmsh/tsm/business/exception/BusinessException$ErrorMessage;)V
    //   147: athrow
    //   148: astore 19
    //   150: aload_0
    //   151: getfield 19	cn/com/fmsh/tsm/business/core/BusinessExtendImpl:a	Lcn/com/fmsh/util/log/FMLog;
    //   154: ifnull +50 -> 204
    //   157: aload_0
    //   158: getfield 19	cn/com/fmsh/tsm/business/core/BusinessExtendImpl:a	Lcn/com/fmsh/util/log/FMLog;
    //   161: aload_0
    //   162: getfield 29	cn/com/fmsh/tsm/business/core/BusinessExtendImpl:b	Ljava/lang/String;
    //   165: new 71	java/lang/StringBuilder
    //   168: dup
    //   169: aload_3
    //   170: invokestatic 77	java/lang/String:valueOf	(Ljava/lang/Object;)Ljava/lang/String;
    //   173: invokespecial 80	java/lang/StringBuilder:<init>	(Ljava/lang/String;)V
    //   176: iconst_5
    //   177: bipush 8
    //   179: ldc_w 333
    //   182: invokestatic 122	cn/com/fmsh/util/FM_Utils:copyValueOf	(IILjava/lang/String;)Ljava/lang/String;
    //   185: invokevirtual 92	java/lang/StringBuilder:append	(Ljava/lang/String;)Ljava/lang/StringBuilder;
    //   188: aload 15
    //   190: invokestatic 141	cn/com/fmsh/util/FM_Bytes:bytesToHexString	([B)Ljava/lang/String;
    //   193: invokevirtual 92	java/lang/StringBuilder:append	(Ljava/lang/String;)Ljava/lang/StringBuilder;
    //   196: invokevirtual 95	java/lang/StringBuilder:toString	()Ljava/lang/String;
    //   199: invokeinterface 98 3 0
    //   204: aload_0
    //   205: getfield 31	cn/com/fmsh/tsm/business/core/BusinessExtendImpl:c	Lcn/com/fmsh/tsm/business/core/CardBusinessBasic;
    //   208: new 71	java/lang/StringBuilder
    //   211: dup
    //   212: aload_3
    //   213: invokestatic 77	java/lang/String:valueOf	(Ljava/lang/Object;)Ljava/lang/String;
    //   216: invokespecial 80	java/lang/StringBuilder:<init>	(Ljava/lang/String;)V
    //   219: sipush 200
    //   222: ldc_w 335
    //   225: invokestatic 63	cn/com/fmsh/util/FM_Int:lastIndexOf	(ILjava/lang/String;)Ljava/lang/String;
    //   228: invokevirtual 92	java/lang/StringBuilder:append	(Ljava/lang/String;)Ljava/lang/StringBuilder;
    //   231: invokevirtual 95	java/lang/StringBuilder:toString	()Ljava/lang/String;
    //   234: getstatic 321	cn/com/fmsh/tsm/business/exception/BusinessException$ErrorMessage:local_message_command_data_invaild	Lcn/com/fmsh/tsm/business/exception/BusinessException$ErrorMessage;
    //   237: iconst_0
    //   238: invokevirtual 193	cn/com/fmsh/tsm/business/core/CardBusinessBasic:throwExceptionAndClose	(Ljava/lang/String;Lcn/com/fmsh/tsm/business/exception/BusinessException$ErrorMessage;Z)V
    //   241: aload 16
    //   243: areturn
    //   244: aload_0
    //   245: getfield 31	cn/com/fmsh/tsm/business/core/BusinessExtendImpl:c	Lcn/com/fmsh/tsm/business/core/CardBusinessBasic;
    //   248: sipush 1151
    //   251: invokevirtual 153	cn/com/fmsh/tsm/business/core/CardBusinessBasic:getServer4Business	(I)Ljava/lang/String;
    //   254: astore 5
    //   256: aload 5
    //   258: ifnonnull +622 -> 880
    //   261: aload_0
    //   262: getfield 19	cn/com/fmsh/tsm/business/core/BusinessExtendImpl:a	Lcn/com/fmsh/util/log/FMLog;
    //   265: ifnull +44 -> 309
    //   268: aload_0
    //   269: getfield 19	cn/com/fmsh/tsm/business/core/BusinessExtendImpl:a	Lcn/com/fmsh/util/log/FMLog;
    //   272: aload_0
    //   273: getfield 29	cn/com/fmsh/tsm/business/core/BusinessExtendImpl:b	Ljava/lang/String;
    //   276: new 71	java/lang/StringBuilder
    //   279: dup
    //   280: aload_3
    //   281: invokestatic 77	java/lang/String:valueOf	(Ljava/lang/Object;)Ljava/lang/String;
    //   284: invokespecial 80	java/lang/StringBuilder:<init>	(Ljava/lang/String;)V
    //   287: sipush 214
    //   290: bipush 54
    //   292: ldc_w 337
    //   295: invokestatic 122	cn/com/fmsh/util/FM_Utils:copyValueOf	(IILjava/lang/String;)Ljava/lang/String;
    //   298: invokevirtual 92	java/lang/StringBuilder:append	(Ljava/lang/String;)Ljava/lang/StringBuilder;
    //   301: invokevirtual 95	java/lang/StringBuilder:toString	()Ljava/lang/String;
    //   304: invokeinterface 98 3 0
    //   309: new 45	cn/com/fmsh/tsm/business/exception/BusinessException
    //   312: dup
    //   313: new 71	java/lang/StringBuilder
    //   316: dup
    //   317: aload_3
    //   318: invokestatic 77	java/lang/String:valueOf	(Ljava/lang/Object;)Ljava/lang/String;
    //   321: invokespecial 80	java/lang/StringBuilder:<init>	(Ljava/lang/String;)V
    //   324: ldc_w 339
    //   327: sipush 176
    //   330: bipush 55
    //   332: invokestatic 106	cn/com/fmsh/util/FM_Bytes:startsWith	(Ljava/lang/String;II)Ljava/lang/String;
    //   335: invokevirtual 92	java/lang/StringBuilder:append	(Ljava/lang/String;)Ljava/lang/StringBuilder;
    //   338: invokevirtual 95	java/lang/StringBuilder:toString	()Ljava/lang/String;
    //   341: getstatic 168	cn/com/fmsh/tsm/business/exception/BusinessException$ErrorMessage:local_app_query_server_fail	Lcn/com/fmsh/tsm/business/exception/BusinessException$ErrorMessage;
    //   344: invokespecial 115	cn/com/fmsh/tsm/business/exception/BusinessException:<init>	(Ljava/lang/String;Lcn/com/fmsh/tsm/business/exception/BusinessException$ErrorMessage;)V
    //   347: athrow
    //   348: aload_2
    //   349: ifnonnull -105 -> 244
    //   352: aload_0
    //   353: getfield 19	cn/com/fmsh/tsm/business/core/BusinessExtendImpl:a	Lcn/com/fmsh/util/log/FMLog;
    //   356: ifnull +42 -> 398
    //   359: aload_0
    //   360: getfield 19	cn/com/fmsh/tsm/business/core/BusinessExtendImpl:a	Lcn/com/fmsh/util/log/FMLog;
    //   363: aload_0
    //   364: getfield 29	cn/com/fmsh/tsm/business/core/BusinessExtendImpl:b	Ljava/lang/String;
    //   367: new 71	java/lang/StringBuilder
    //   370: dup
    //   371: aload_3
    //   372: invokestatic 77	java/lang/String:valueOf	(Ljava/lang/Object;)Ljava/lang/String;
    //   375: invokespecial 80	java/lang/StringBuilder:<init>	(Ljava/lang/String;)V
    //   378: ldc_w 341
    //   381: sipush 144
    //   384: invokestatic 55	cn/com/fmsh/util/FM_Long:concat	(Ljava/lang/String;I)Ljava/lang/String;
    //   387: invokevirtual 92	java/lang/StringBuilder:append	(Ljava/lang/String;)Ljava/lang/StringBuilder;
    //   390: invokevirtual 95	java/lang/StringBuilder:toString	()Ljava/lang/String;
    //   393: invokeinterface 98 3 0
    //   398: new 45	cn/com/fmsh/tsm/business/exception/BusinessException
    //   401: dup
    //   402: new 71	java/lang/StringBuilder
    //   405: dup
    //   406: aload_3
    //   407: invokestatic 77	java/lang/String:valueOf	(Ljava/lang/Object;)Ljava/lang/String;
    //   410: invokespecial 80	java/lang/StringBuilder:<init>	(Ljava/lang/String;)V
    //   413: ldc_w 343
    //   416: iconst_3
    //   417: invokestatic 55	cn/com/fmsh/util/FM_Long:concat	(Ljava/lang/String;I)Ljava/lang/String;
    //   420: invokevirtual 92	java/lang/StringBuilder:append	(Ljava/lang/String;)Ljava/lang/StringBuilder;
    //   423: invokevirtual 95	java/lang/StringBuilder:toString	()Ljava/lang/String;
    //   426: getstatic 127	cn/com/fmsh/tsm/business/exception/BusinessException$ErrorMessage:local_message_load_config_fail	Lcn/com/fmsh/tsm/business/exception/BusinessException$ErrorMessage;
    //   429: invokespecial 115	cn/com/fmsh/tsm/business/exception/BusinessException:<init>	(Ljava/lang/String;Lcn/com/fmsh/tsm/business/exception/BusinessException$ErrorMessage;)V
    //   432: athrow
    //   433: aload_0
    //   434: getfield 31	cn/com/fmsh/tsm/business/core/BusinessExtendImpl:c	Lcn/com/fmsh/tsm/business/core/CardBusinessBasic;
    //   437: invokevirtual 172	cn/com/fmsh/tsm/business/core/CardBusinessBasic:getMessageHandler	()Lcn/com/fmsh/communication/message/IMessageHandler;
    //   440: astore 4
    //   442: aload 4
    //   444: ifnonnull +537 -> 981
    //   447: aload_0
    //   448: getfield 19	cn/com/fmsh/tsm/business/core/BusinessExtendImpl:a	Lcn/com/fmsh/util/log/FMLog;
    //   451: ifnull +42 -> 493
    //   454: aload_0
    //   455: getfield 19	cn/com/fmsh/tsm/business/core/BusinessExtendImpl:a	Lcn/com/fmsh/util/log/FMLog;
    //   458: aload_0
    //   459: getfield 29	cn/com/fmsh/tsm/business/core/BusinessExtendImpl:b	Ljava/lang/String;
    //   462: new 71	java/lang/StringBuilder
    //   465: dup
    //   466: aload_3
    //   467: invokestatic 77	java/lang/String:valueOf	(Ljava/lang/Object;)Ljava/lang/String;
    //   470: invokespecial 80	java/lang/StringBuilder:<init>	(Ljava/lang/String;)V
    //   473: ldc_w 345
    //   476: iconst_4
    //   477: bipush 100
    //   479: invokestatic 316	cn/com/fmsh/util/Util4Java:toString	(Ljava/lang/String;II)Ljava/lang/String;
    //   482: invokevirtual 92	java/lang/StringBuilder:append	(Ljava/lang/String;)Ljava/lang/StringBuilder;
    //   485: invokevirtual 95	java/lang/StringBuilder:toString	()Ljava/lang/String;
    //   488: invokeinterface 98 3 0
    //   493: new 45	cn/com/fmsh/tsm/business/exception/BusinessException
    //   496: dup
    //   497: new 71	java/lang/StringBuilder
    //   500: dup
    //   501: aload_3
    //   502: invokestatic 77	java/lang/String:valueOf	(Ljava/lang/Object;)Ljava/lang/String;
    //   505: invokespecial 80	java/lang/StringBuilder:<init>	(Ljava/lang/String;)V
    //   508: ldc_w 347
    //   511: iconst_4
    //   512: invokestatic 55	cn/com/fmsh/util/FM_Long:concat	(Ljava/lang/String;I)Ljava/lang/String;
    //   515: invokevirtual 92	java/lang/StringBuilder:append	(Ljava/lang/String;)Ljava/lang/StringBuilder;
    //   518: invokevirtual 95	java/lang/StringBuilder:toString	()Ljava/lang/String;
    //   521: getstatic 127	cn/com/fmsh/tsm/business/exception/BusinessException$ErrorMessage:local_message_load_config_fail	Lcn/com/fmsh/tsm/business/exception/BusinessException$ErrorMessage;
    //   524: invokespecial 115	cn/com/fmsh/tsm/business/exception/BusinessException:<init>	(Ljava/lang/String;Lcn/com/fmsh/tsm/business/exception/BusinessException$ErrorMessage;)V
    //   527: athrow
    //   528: astore 20
    //   530: aload_0
    //   531: getfield 19	cn/com/fmsh/tsm/business/core/BusinessExtendImpl:a	Lcn/com/fmsh/util/log/FMLog;
    //   534: ifnull +50 -> 584
    //   537: aload_0
    //   538: getfield 19	cn/com/fmsh/tsm/business/core/BusinessExtendImpl:a	Lcn/com/fmsh/util/log/FMLog;
    //   541: aload_0
    //   542: getfield 29	cn/com/fmsh/tsm/business/core/BusinessExtendImpl:b	Ljava/lang/String;
    //   545: new 71	java/lang/StringBuilder
    //   548: dup
    //   549: aload_3
    //   550: invokestatic 77	java/lang/String:valueOf	(Ljava/lang/Object;)Ljava/lang/String;
    //   553: invokespecial 80	java/lang/StringBuilder:<init>	(Ljava/lang/String;)V
    //   556: ldc_w 349
    //   559: iconst_2
    //   560: bipush 110
    //   562: invokestatic 160	cn/com/fmsh/util/BCCUtil:endsWith	(Ljava/lang/String;II)Ljava/lang/String;
    //   565: invokevirtual 92	java/lang/StringBuilder:append	(Ljava/lang/String;)Ljava/lang/StringBuilder;
    //   568: aload 20
    //   570: invokestatic 184	cn/com/fmsh/util/Util4Java:getExceptionInfo	(Ljava/lang/Exception;)Ljava/lang/String;
    //   573: invokevirtual 92	java/lang/StringBuilder:append	(Ljava/lang/String;)Ljava/lang/StringBuilder;
    //   576: invokevirtual 95	java/lang/StringBuilder:toString	()Ljava/lang/String;
    //   579: invokeinterface 98 3 0
    //   584: aload_0
    //   585: getfield 31	cn/com/fmsh/tsm/business/core/BusinessExtendImpl:c	Lcn/com/fmsh/tsm/business/core/CardBusinessBasic;
    //   588: new 71	java/lang/StringBuilder
    //   591: dup
    //   592: aload_3
    //   593: invokestatic 77	java/lang/String:valueOf	(Ljava/lang/Object;)Ljava/lang/String;
    //   596: invokespecial 80	java/lang/StringBuilder:<init>	(Ljava/lang/String;)V
    //   599: ldc_w 351
    //   602: sipush 228
    //   605: invokestatic 55	cn/com/fmsh/util/FM_Long:concat	(Ljava/lang/String;I)Ljava/lang/String;
    //   608: invokevirtual 92	java/lang/StringBuilder:append	(Ljava/lang/String;)Ljava/lang/StringBuilder;
    //   611: invokevirtual 95	java/lang/StringBuilder:toString	()Ljava/lang/String;
    //   614: getstatic 189	cn/com/fmsh/tsm/business/exception/BusinessException$ErrorMessage:local_message_message_handle_exception	Lcn/com/fmsh/tsm/business/exception/BusinessException$ErrorMessage;
    //   617: iconst_0
    //   618: invokevirtual 193	cn/com/fmsh/tsm/business/core/CardBusinessBasic:throwExceptionAndClose	(Ljava/lang/String;Lcn/com/fmsh/tsm/business/exception/BusinessException$ErrorMessage;Z)V
    //   621: aload_0
    //   622: getfield 31	cn/com/fmsh/tsm/business/core/BusinessExtendImpl:c	Lcn/com/fmsh/tsm/business/core/CardBusinessBasic;
    //   625: aload 6
    //   627: aload_3
    //   628: iconst_0
    //   629: aload 5
    //   631: invokevirtual 197	cn/com/fmsh/tsm/business/core/CardBusinessBasic:interaction	([BLjava/lang/String;ZLjava/lang/String;)[B
    //   634: astore 15
    //   636: getstatic 209	cn/com/fmsh/tsm/business/constants/Constants$RespCodeonse4Platform:SUCESS	[B
    //   639: aload 15
    //   641: iconst_2
    //   642: invokestatic 261	java/util/Arrays:copyOf	([BI)[B
    //   645: invokestatic 215	java/util/Arrays:equals	([B[B)Z
    //   648: ifne +95 -> 743
    //   651: aload_0
    //   652: getfield 19	cn/com/fmsh/tsm/business/core/BusinessExtendImpl:a	Lcn/com/fmsh/util/log/FMLog;
    //   655: ifnull +50 -> 705
    //   658: aload_0
    //   659: getfield 19	cn/com/fmsh/tsm/business/core/BusinessExtendImpl:a	Lcn/com/fmsh/util/log/FMLog;
    //   662: aload_0
    //   663: getfield 29	cn/com/fmsh/tsm/business/core/BusinessExtendImpl:b	Ljava/lang/String;
    //   666: new 71	java/lang/StringBuilder
    //   669: dup
    //   670: aload_3
    //   671: invokestatic 77	java/lang/String:valueOf	(Ljava/lang/Object;)Ljava/lang/String;
    //   674: invokespecial 80	java/lang/StringBuilder:<init>	(Ljava/lang/String;)V
    //   677: ldc_w 353
    //   680: iconst_5
    //   681: bipush 109
    //   683: invokestatic 106	cn/com/fmsh/util/FM_Bytes:startsWith	(Ljava/lang/String;II)Ljava/lang/String;
    //   686: invokevirtual 92	java/lang/StringBuilder:append	(Ljava/lang/String;)Ljava/lang/StringBuilder;
    //   689: aload 15
    //   691: invokestatic 141	cn/com/fmsh/util/FM_Bytes:bytesToHexString	([B)Ljava/lang/String;
    //   694: invokevirtual 92	java/lang/StringBuilder:append	(Ljava/lang/String;)Ljava/lang/StringBuilder;
    //   697: invokevirtual 95	java/lang/StringBuilder:toString	()Ljava/lang/String;
    //   700: invokeinterface 266 3 0
    //   705: aload_0
    //   706: getfield 31	cn/com/fmsh/tsm/business/core/BusinessExtendImpl:c	Lcn/com/fmsh/tsm/business/core/CardBusinessBasic;
    //   709: new 71	java/lang/StringBuilder
    //   712: dup
    //   713: aload_3
    //   714: invokestatic 77	java/lang/String:valueOf	(Ljava/lang/Object;)Ljava/lang/String;
    //   717: invokespecial 80	java/lang/StringBuilder:<init>	(Ljava/lang/String;)V
    //   720: ldc_w 355
    //   723: bipush 126
    //   725: bipush 99
    //   727: invokestatic 160	cn/com/fmsh/util/BCCUtil:endsWith	(Ljava/lang/String;II)Ljava/lang/String;
    //   730: invokevirtual 92	java/lang/StringBuilder:append	(Ljava/lang/String;)Ljava/lang/StringBuilder;
    //   733: invokevirtual 95	java/lang/StringBuilder:toString	()Ljava/lang/String;
    //   736: getstatic 271	cn/com/fmsh/tsm/business/exception/BusinessException$ErrorMessage:local_message_platform_business_handle_fail	Lcn/com/fmsh/tsm/business/exception/BusinessException$ErrorMessage;
    //   739: iconst_1
    //   740: invokevirtual 193	cn/com/fmsh/tsm/business/core/CardBusinessBasic:throwExceptionAndClose	(Ljava/lang/String;Lcn/com/fmsh/tsm/business/exception/BusinessException$ErrorMessage;Z)V
    //   743: aconst_null
    //   744: astore 16
    //   746: aload 4
    //   748: sipush 4631
    //   751: aload 15
    //   753: iconst_2
    //   754: aload 15
    //   756: arraylength
    //   757: invokestatic 278	java/util/Arrays:copyOfRange	([BII)[B
    //   760: invokeinterface 281 3 0
    //   765: bipush 107
    //   767: invokeinterface 285 2 0
    //   772: astore 17
    //   774: aload 17
    //   776: ifnonnull +90 -> 866
    //   779: aload_0
    //   780: getfield 19	cn/com/fmsh/tsm/business/core/BusinessExtendImpl:a	Lcn/com/fmsh/util/log/FMLog;
    //   783: ifnull +44 -> 827
    //   786: aload_0
    //   787: getfield 19	cn/com/fmsh/tsm/business/core/BusinessExtendImpl:a	Lcn/com/fmsh/util/log/FMLog;
    //   790: aload_0
    //   791: getfield 29	cn/com/fmsh/tsm/business/core/BusinessExtendImpl:b	Ljava/lang/String;
    //   794: new 71	java/lang/StringBuilder
    //   797: dup
    //   798: aload_3
    //   799: invokestatic 77	java/lang/String:valueOf	(Ljava/lang/Object;)Ljava/lang/String;
    //   802: invokespecial 80	java/lang/StringBuilder:<init>	(Ljava/lang/String;)V
    //   805: ldc_w 357
    //   808: sipush 186
    //   811: bipush 120
    //   813: invokestatic 316	cn/com/fmsh/util/Util4Java:toString	(Ljava/lang/String;II)Ljava/lang/String;
    //   816: invokevirtual 92	java/lang/StringBuilder:append	(Ljava/lang/String;)Ljava/lang/StringBuilder;
    //   819: invokevirtual 95	java/lang/StringBuilder:toString	()Ljava/lang/String;
    //   822: invokeinterface 98 3 0
    //   827: aload_0
    //   828: getfield 31	cn/com/fmsh/tsm/business/core/BusinessExtendImpl:c	Lcn/com/fmsh/tsm/business/core/CardBusinessBasic;
    //   831: new 71	java/lang/StringBuilder
    //   834: dup
    //   835: aload_3
    //   836: invokestatic 77	java/lang/String:valueOf	(Ljava/lang/Object;)Ljava/lang/String;
    //   839: invokespecial 80	java/lang/StringBuilder:<init>	(Ljava/lang/String;)V
    //   842: sipush 280
    //   845: bipush 74
    //   847: ldc_w 359
    //   850: invokestatic 88	cn/com/fmsh/FM_Exception:getChars	(IILjava/lang/String;)Ljava/lang/String;
    //   853: invokevirtual 92	java/lang/StringBuilder:append	(Ljava/lang/String;)Ljava/lang/StringBuilder;
    //   856: invokevirtual 95	java/lang/StringBuilder:toString	()Ljava/lang/String;
    //   859: getstatic 321	cn/com/fmsh/tsm/business/exception/BusinessException$ErrorMessage:local_message_command_data_invaild	Lcn/com/fmsh/tsm/business/exception/BusinessException$ErrorMessage;
    //   862: iconst_0
    //   863: invokevirtual 193	cn/com/fmsh/tsm/business/core/CardBusinessBasic:throwExceptionAndClose	(Ljava/lang/String;Lcn/com/fmsh/tsm/business/exception/BusinessException$ErrorMessage;Z)V
    //   866: aload 17
    //   868: invokestatic 365	cn/com/fmsh/tsm/business/bean/ElectronicTakeUp:fromTag	(Lcn/com/fmsh/communication/message/ITag;)Lcn/com/fmsh/tsm/business/bean/ElectronicTakeUp;
    //   871: astore 18
    //   873: aload 18
    //   875: astore 16
    //   877: goto -636 -> 241
    //   880: aload_0
    //   881: getfield 31	cn/com/fmsh/tsm/business/core/BusinessExtendImpl:c	Lcn/com/fmsh/tsm/business/core/CardBusinessBasic;
    //   884: aload_3
    //   885: aload 5
    //   887: invokevirtual 218	cn/com/fmsh/tsm/business/core/CardBusinessBasic:businessReady	(Ljava/lang/String;Ljava/lang/String;)V
    //   890: aconst_null
    //   891: astore 6
    //   893: aload 4
    //   895: sipush 4631
    //   898: invokeinterface 224 2 0
    //   903: astore 7
    //   905: aload 4
    //   907: bipush 112
    //   909: invokeinterface 228 2 0
    //   914: astore 8
    //   916: aload 8
    //   918: aload_1
    //   919: invokeinterface 233 2 0
    //   924: pop
    //   925: aload 7
    //   927: aload 8
    //   929: invokeinterface 239 2 0
    //   934: pop
    //   935: aload 4
    //   937: bipush 113
    //   939: invokeinterface 228 2 0
    //   944: astore 11
    //   946: aload 11
    //   948: aload_2
    //   949: invokeinterface 233 2 0
    //   954: pop
    //   955: aload 7
    //   957: aload 11
    //   959: invokeinterface 239 2 0
    //   964: pop
    //   965: aload 7
    //   967: invokeinterface 243 1 0
    //   972: astore 14
    //   974: aload 14
    //   976: astore 6
    //   978: goto -357 -> 621
    //   981: aload_1
    //   982: ifnonnull -634 -> 348
    //   985: aload_0
    //   986: getfield 19	cn/com/fmsh/tsm/business/core/BusinessExtendImpl:a	Lcn/com/fmsh/util/log/FMLog;
    //   989: ifnull +40 -> 1029
    //   992: aload_0
    //   993: getfield 19	cn/com/fmsh/tsm/business/core/BusinessExtendImpl:a	Lcn/com/fmsh/util/log/FMLog;
    //   996: aload_0
    //   997: getfield 29	cn/com/fmsh/tsm/business/core/BusinessExtendImpl:b	Ljava/lang/String;
    //   1000: new 71	java/lang/StringBuilder
    //   1003: dup
    //   1004: aload_3
    //   1005: invokestatic 77	java/lang/String:valueOf	(Ljava/lang/Object;)Ljava/lang/String;
    //   1008: invokespecial 80	java/lang/StringBuilder:<init>	(Ljava/lang/String;)V
    //   1011: iconst_2
    //   1012: ldc_w 367
    //   1015: invokestatic 137	cn/com/fmsh/util/CRCUtil:valueOf	(ILjava/lang/String;)Ljava/lang/String;
    //   1018: invokevirtual 92	java/lang/StringBuilder:append	(Ljava/lang/String;)Ljava/lang/StringBuilder;
    //   1021: invokevirtual 95	java/lang/StringBuilder:toString	()Ljava/lang/String;
    //   1024: invokeinterface 98 3 0
    //   1029: new 45	cn/com/fmsh/tsm/business/exception/BusinessException
    //   1032: dup
    //   1033: new 71	java/lang/StringBuilder
    //   1036: dup
    //   1037: aload_3
    //   1038: invokestatic 77	java/lang/String:valueOf	(Ljava/lang/Object;)Ljava/lang/String;
    //   1041: invokespecial 80	java/lang/StringBuilder:<init>	(Ljava/lang/String;)V
    //   1044: iconst_4
    //   1045: ldc_w 369
    //   1048: invokestatic 63	cn/com/fmsh/util/FM_Int:lastIndexOf	(ILjava/lang/String;)Ljava/lang/String;
    //   1051: invokevirtual 92	java/lang/StringBuilder:append	(Ljava/lang/String;)Ljava/lang/StringBuilder;
    //   1054: invokevirtual 95	java/lang/StringBuilder:toString	()Ljava/lang/String;
    //   1057: getstatic 127	cn/com/fmsh/tsm/business/exception/BusinessException$ErrorMessage:local_message_load_config_fail	Lcn/com/fmsh/tsm/business/exception/BusinessException$ErrorMessage;
    //   1060: invokespecial 115	cn/com/fmsh/tsm/business/exception/BusinessException:<init>	(Ljava/lang/String;Lcn/com/fmsh/tsm/business/exception/BusinessException$ErrorMessage;)V
    //   1063: athrow
    //
    // Exception table:
    //   from	to	target	type
    //   746	873	148	cn/com/fmsh/communication/message/exception/FMCommunicationMessageException
    //   905	974	528	cn/com/fmsh/communication/message/exception/FMCommunicationMessageException
  }

  // ERROR //
  public java.util.List<cn.com.fmsh.tsm.business.bean.ElectronicTakeUp> queryElectronicTakeUps(byte[] paramArrayOfByte, byte paramByte, int paramInt)
    throws cn.com.fmsh.tsm.business.exception.BusinessException
  {
    // Byte code:
    //   0: bipush 122
    //   2: ldc_w 373
    //   5: invokestatic 137	cn/com/fmsh/util/CRCUtil:valueOf	(ILjava/lang/String;)Ljava/lang/String;
    //   8: astore 4
    //   10: aload_0
    //   11: getfield 19	cn/com/fmsh/tsm/business/core/BusinessExtendImpl:a	Lcn/com/fmsh/util/log/FMLog;
    //   14: ifnonnull +13 -> 27
    //   17: aload_0
    //   18: invokestatic 37	cn/com/fmsh/util/log/LogFactory:getInstance	()Lcn/com/fmsh/util/log/LogFactory;
    //   21: invokevirtual 41	cn/com/fmsh/util/log/LogFactory:getLog	()Lcn/com/fmsh/util/log/FMLog;
    //   24: putfield 19	cn/com/fmsh/tsm/business/core/BusinessExtendImpl:a	Lcn/com/fmsh/util/log/FMLog;
    //   27: aload_0
    //   28: getfield 19	cn/com/fmsh/tsm/business/core/BusinessExtendImpl:a	Lcn/com/fmsh/util/log/FMLog;
    //   31: ifnull +27 -> 58
    //   34: aload_0
    //   35: getfield 19	cn/com/fmsh/tsm/business/core/BusinessExtendImpl:a	Lcn/com/fmsh/util/log/FMLog;
    //   38: aload_0
    //   39: getfield 29	cn/com/fmsh/tsm/business/core/BusinessExtendImpl:b	Ljava/lang/String;
    //   42: ldc_w 375
    //   45: sipush 238
    //   48: bipush 18
    //   50: invokestatic 316	cn/com/fmsh/util/Util4Java:toString	(Ljava/lang/String;II)Ljava/lang/String;
    //   53: invokeinterface 69 3 0
    //   58: aload_0
    //   59: getfield 31	cn/com/fmsh/tsm/business/core/BusinessExtendImpl:c	Lcn/com/fmsh/tsm/business/core/CardBusinessBasic;
    //   62: ifnonnull +862 -> 924
    //   65: aload_0
    //   66: getfield 19	cn/com/fmsh/tsm/business/core/BusinessExtendImpl:a	Lcn/com/fmsh/util/log/FMLog;
    //   69: ifnull +43 -> 112
    //   72: aload_0
    //   73: getfield 19	cn/com/fmsh/tsm/business/core/BusinessExtendImpl:a	Lcn/com/fmsh/util/log/FMLog;
    //   76: aload_0
    //   77: getfield 29	cn/com/fmsh/tsm/business/core/BusinessExtendImpl:b	Ljava/lang/String;
    //   80: new 71	java/lang/StringBuilder
    //   83: dup
    //   84: aload 4
    //   86: invokestatic 77	java/lang/String:valueOf	(Ljava/lang/Object;)Ljava/lang/String;
    //   89: invokespecial 80	java/lang/StringBuilder:<init>	(Ljava/lang/String;)V
    //   92: iconst_3
    //   93: bipush 94
    //   95: ldc_w 377
    //   98: invokestatic 88	cn/com/fmsh/FM_Exception:getChars	(IILjava/lang/String;)Ljava/lang/String;
    //   101: invokevirtual 92	java/lang/StringBuilder:append	(Ljava/lang/String;)Ljava/lang/StringBuilder;
    //   104: invokevirtual 95	java/lang/StringBuilder:toString	()Ljava/lang/String;
    //   107: invokeinterface 98 3 0
    //   112: new 45	cn/com/fmsh/tsm/business/exception/BusinessException
    //   115: dup
    //   116: new 71	java/lang/StringBuilder
    //   119: dup
    //   120: aload 4
    //   122: invokestatic 77	java/lang/String:valueOf	(Ljava/lang/Object;)Ljava/lang/String;
    //   125: invokespecial 80	java/lang/StringBuilder:<init>	(Ljava/lang/String;)V
    //   128: ldc_w 379
    //   131: iconst_5
    //   132: bipush 15
    //   134: invokestatic 316	cn/com/fmsh/util/Util4Java:toString	(Ljava/lang/String;II)Ljava/lang/String;
    //   137: invokevirtual 92	java/lang/StringBuilder:append	(Ljava/lang/String;)Ljava/lang/StringBuilder;
    //   140: invokevirtual 95	java/lang/StringBuilder:toString	()Ljava/lang/String;
    //   143: getstatic 112	cn/com/fmsh/tsm/business/exception/BusinessException$ErrorMessage:local_business_init_fail	Lcn/com/fmsh/tsm/business/exception/BusinessException$ErrorMessage;
    //   146: invokespecial 115	cn/com/fmsh/tsm/business/exception/BusinessException:<init>	(Ljava/lang/String;Lcn/com/fmsh/tsm/business/exception/BusinessException$ErrorMessage;)V
    //   149: athrow
    //   150: astore 27
    //   152: aload_0
    //   153: getfield 19	cn/com/fmsh/tsm/business/core/BusinessExtendImpl:a	Lcn/com/fmsh/util/log/FMLog;
    //   156: ifnull +50 -> 206
    //   159: aload_0
    //   160: getfield 19	cn/com/fmsh/tsm/business/core/BusinessExtendImpl:a	Lcn/com/fmsh/util/log/FMLog;
    //   163: aload_0
    //   164: getfield 29	cn/com/fmsh/tsm/business/core/BusinessExtendImpl:b	Ljava/lang/String;
    //   167: new 71	java/lang/StringBuilder
    //   170: dup
    //   171: aload 4
    //   173: invokestatic 77	java/lang/String:valueOf	(Ljava/lang/Object;)Ljava/lang/String;
    //   176: invokespecial 80	java/lang/StringBuilder:<init>	(Ljava/lang/String;)V
    //   179: bipush 58
    //   181: ldc_w 381
    //   184: invokestatic 137	cn/com/fmsh/util/CRCUtil:valueOf	(ILjava/lang/String;)Ljava/lang/String;
    //   187: invokevirtual 92	java/lang/StringBuilder:append	(Ljava/lang/String;)Ljava/lang/StringBuilder;
    //   190: aload 27
    //   192: invokestatic 184	cn/com/fmsh/util/Util4Java:getExceptionInfo	(Ljava/lang/Exception;)Ljava/lang/String;
    //   195: invokevirtual 92	java/lang/StringBuilder:append	(Ljava/lang/String;)Ljava/lang/StringBuilder;
    //   198: invokevirtual 95	java/lang/StringBuilder:toString	()Ljava/lang/String;
    //   201: invokeinterface 98 3 0
    //   206: aload_0
    //   207: getfield 31	cn/com/fmsh/tsm/business/core/BusinessExtendImpl:c	Lcn/com/fmsh/tsm/business/core/CardBusinessBasic;
    //   210: new 71	java/lang/StringBuilder
    //   213: dup
    //   214: aload 4
    //   216: invokestatic 77	java/lang/String:valueOf	(Ljava/lang/Object;)Ljava/lang/String;
    //   219: invokespecial 80	java/lang/StringBuilder:<init>	(Ljava/lang/String;)V
    //   222: sipush 278
    //   225: bipush 118
    //   227: ldc_w 383
    //   230: invokestatic 122	cn/com/fmsh/util/FM_Utils:copyValueOf	(IILjava/lang/String;)Ljava/lang/String;
    //   233: invokevirtual 92	java/lang/StringBuilder:append	(Ljava/lang/String;)Ljava/lang/StringBuilder;
    //   236: invokevirtual 95	java/lang/StringBuilder:toString	()Ljava/lang/String;
    //   239: getstatic 189	cn/com/fmsh/tsm/business/exception/BusinessException$ErrorMessage:local_message_message_handle_exception	Lcn/com/fmsh/tsm/business/exception/BusinessException$ErrorMessage;
    //   242: iconst_0
    //   243: invokevirtual 193	cn/com/fmsh/tsm/business/core/CardBusinessBasic:throwExceptionAndClose	(Ljava/lang/String;Lcn/com/fmsh/tsm/business/exception/BusinessException$ErrorMessage;Z)V
    //   246: aload_0
    //   247: getfield 31	cn/com/fmsh/tsm/business/core/BusinessExtendImpl:c	Lcn/com/fmsh/tsm/business/core/CardBusinessBasic;
    //   250: aload 7
    //   252: aload 4
    //   254: iconst_0
    //   255: aload 6
    //   257: invokevirtual 197	cn/com/fmsh/tsm/business/core/CardBusinessBasic:interaction	([BLjava/lang/String;ZLjava/lang/String;)[B
    //   260: astore 16
    //   262: aload 16
    //   264: iconst_2
    //   265: invokestatic 261	java/util/Arrays:copyOf	([BI)[B
    //   268: astore 17
    //   270: getstatic 209	cn/com/fmsh/tsm/business/constants/Constants$RespCodeonse4Platform:SUCESS	[B
    //   273: aload 17
    //   275: invokestatic 215	java/util/Arrays:equals	([B[B)Z
    //   278: ifne +99 -> 377
    //   281: aload_0
    //   282: getfield 19	cn/com/fmsh/tsm/business/core/BusinessExtendImpl:a	Lcn/com/fmsh/util/log/FMLog;
    //   285: ifnull +51 -> 336
    //   288: aload_0
    //   289: getfield 19	cn/com/fmsh/tsm/business/core/BusinessExtendImpl:a	Lcn/com/fmsh/util/log/FMLog;
    //   292: aload_0
    //   293: getfield 29	cn/com/fmsh/tsm/business/core/BusinessExtendImpl:b	Ljava/lang/String;
    //   296: new 71	java/lang/StringBuilder
    //   299: dup
    //   300: aload 4
    //   302: invokestatic 77	java/lang/String:valueOf	(Ljava/lang/Object;)Ljava/lang/String;
    //   305: invokespecial 80	java/lang/StringBuilder:<init>	(Ljava/lang/String;)V
    //   308: iconst_4
    //   309: bipush 13
    //   311: ldc_w 385
    //   314: invokestatic 88	cn/com/fmsh/FM_Exception:getChars	(IILjava/lang/String;)Ljava/lang/String;
    //   317: invokevirtual 92	java/lang/StringBuilder:append	(Ljava/lang/String;)Ljava/lang/StringBuilder;
    //   320: aload 16
    //   322: invokestatic 141	cn/com/fmsh/util/FM_Bytes:bytesToHexString	([B)Ljava/lang/String;
    //   325: invokevirtual 92	java/lang/StringBuilder:append	(Ljava/lang/String;)Ljava/lang/StringBuilder;
    //   328: invokevirtual 95	java/lang/StringBuilder:toString	()Ljava/lang/String;
    //   331: invokeinterface 266 3 0
    //   336: aload_0
    //   337: getfield 31	cn/com/fmsh/tsm/business/core/BusinessExtendImpl:c	Lcn/com/fmsh/tsm/business/core/CardBusinessBasic;
    //   340: new 71	java/lang/StringBuilder
    //   343: dup
    //   344: aload 4
    //   346: invokestatic 77	java/lang/String:valueOf	(Ljava/lang/Object;)Ljava/lang/String;
    //   349: invokespecial 80	java/lang/StringBuilder:<init>	(Ljava/lang/String;)V
    //   352: ldc_w 387
    //   355: iconst_4
    //   356: invokestatic 55	cn/com/fmsh/util/FM_Long:concat	(Ljava/lang/String;I)Ljava/lang/String;
    //   359: invokevirtual 92	java/lang/StringBuilder:append	(Ljava/lang/String;)Ljava/lang/StringBuilder;
    //   362: invokevirtual 95	java/lang/StringBuilder:toString	()Ljava/lang/String;
    //   365: aload 17
    //   367: invokestatic 141	cn/com/fmsh/util/FM_Bytes:bytesToHexString	([B)Ljava/lang/String;
    //   370: invokestatic 391	cn/com/fmsh/tsm/business/exception/BusinessException$ErrorMessage:instance	(Ljava/lang/String;)Lcn/com/fmsh/tsm/business/exception/BusinessException$ErrorMessage;
    //   373: iconst_1
    //   374: invokevirtual 193	cn/com/fmsh/tsm/business/core/CardBusinessBasic:throwExceptionAndClose	(Ljava/lang/String;Lcn/com/fmsh/tsm/business/exception/BusinessException$ErrorMessage;Z)V
    //   377: new 393	java/util/ArrayList
    //   380: dup
    //   381: invokespecial 394	java/util/ArrayList:<init>	()V
    //   384: astore 18
    //   386: aload 5
    //   388: sipush 1132
    //   391: aload 16
    //   393: iconst_2
    //   394: aload 16
    //   396: arraylength
    //   397: invokestatic 278	java/util/Arrays:copyOfRange	([BII)[B
    //   400: invokeinterface 281 3 0
    //   405: bipush 108
    //   407: invokeinterface 285 2 0
    //   412: astore 20
    //   414: aload 20
    //   416: ifnonnull +337 -> 753
    //   419: aload_0
    //   420: getfield 19	cn/com/fmsh/tsm/business/core/BusinessExtendImpl:a	Lcn/com/fmsh/util/log/FMLog;
    //   423: ifnull +43 -> 466
    //   426: aload_0
    //   427: getfield 19	cn/com/fmsh/tsm/business/core/BusinessExtendImpl:a	Lcn/com/fmsh/util/log/FMLog;
    //   430: aload_0
    //   431: getfield 29	cn/com/fmsh/tsm/business/core/BusinessExtendImpl:b	Ljava/lang/String;
    //   434: new 71	java/lang/StringBuilder
    //   437: dup
    //   438: aload 4
    //   440: invokestatic 77	java/lang/String:valueOf	(Ljava/lang/Object;)Ljava/lang/String;
    //   443: invokespecial 80	java/lang/StringBuilder:<init>	(Ljava/lang/String;)V
    //   446: sipush 180
    //   449: ldc_w 396
    //   452: invokestatic 63	cn/com/fmsh/util/FM_Int:lastIndexOf	(ILjava/lang/String;)Ljava/lang/String;
    //   455: invokevirtual 92	java/lang/StringBuilder:append	(Ljava/lang/String;)Ljava/lang/StringBuilder;
    //   458: invokevirtual 95	java/lang/StringBuilder:toString	()Ljava/lang/String;
    //   461: invokeinterface 98 3 0
    //   466: aload 18
    //   468: areturn
    //   469: astore 19
    //   471: aload_0
    //   472: getfield 19	cn/com/fmsh/tsm/business/core/BusinessExtendImpl:a	Lcn/com/fmsh/util/log/FMLog;
    //   475: ifnull +53 -> 528
    //   478: aload_0
    //   479: getfield 19	cn/com/fmsh/tsm/business/core/BusinessExtendImpl:a	Lcn/com/fmsh/util/log/FMLog;
    //   482: aload_0
    //   483: getfield 29	cn/com/fmsh/tsm/business/core/BusinessExtendImpl:b	Ljava/lang/String;
    //   486: new 71	java/lang/StringBuilder
    //   489: dup
    //   490: aload 4
    //   492: invokestatic 77	java/lang/String:valueOf	(Ljava/lang/Object;)Ljava/lang/String;
    //   495: invokespecial 80	java/lang/StringBuilder:<init>	(Ljava/lang/String;)V
    //   498: ldc_w 398
    //   501: sipush 226
    //   504: bipush 60
    //   506: invokestatic 106	cn/com/fmsh/util/FM_Bytes:startsWith	(Ljava/lang/String;II)Ljava/lang/String;
    //   509: invokevirtual 92	java/lang/StringBuilder:append	(Ljava/lang/String;)Ljava/lang/StringBuilder;
    //   512: aload 16
    //   514: invokestatic 141	cn/com/fmsh/util/FM_Bytes:bytesToHexString	([B)Ljava/lang/String;
    //   517: invokevirtual 92	java/lang/StringBuilder:append	(Ljava/lang/String;)Ljava/lang/StringBuilder;
    //   520: invokevirtual 95	java/lang/StringBuilder:toString	()Ljava/lang/String;
    //   523: invokeinterface 98 3 0
    //   528: aload_0
    //   529: getfield 31	cn/com/fmsh/tsm/business/core/BusinessExtendImpl:c	Lcn/com/fmsh/tsm/business/core/CardBusinessBasic;
    //   532: new 71	java/lang/StringBuilder
    //   535: dup
    //   536: aload 4
    //   538: invokestatic 77	java/lang/String:valueOf	(Ljava/lang/Object;)Ljava/lang/String;
    //   541: invokespecial 80	java/lang/StringBuilder:<init>	(Ljava/lang/String;)V
    //   544: iconst_4
    //   545: bipush 19
    //   547: ldc_w 400
    //   550: invokestatic 122	cn/com/fmsh/util/FM_Utils:copyValueOf	(IILjava/lang/String;)Ljava/lang/String;
    //   553: invokevirtual 92	java/lang/StringBuilder:append	(Ljava/lang/String;)Ljava/lang/StringBuilder;
    //   556: invokevirtual 95	java/lang/StringBuilder:toString	()Ljava/lang/String;
    //   559: getstatic 321	cn/com/fmsh/tsm/business/exception/BusinessException$ErrorMessage:local_message_command_data_invaild	Lcn/com/fmsh/tsm/business/exception/BusinessException$ErrorMessage;
    //   562: iconst_0
    //   563: invokevirtual 193	cn/com/fmsh/tsm/business/core/CardBusinessBasic:throwExceptionAndClose	(Ljava/lang/String;Lcn/com/fmsh/tsm/business/exception/BusinessException$ErrorMessage;Z)V
    //   566: goto -100 -> 466
    //   569: iload_2
    //   570: ifge +252 -> 822
    //   573: aload_0
    //   574: getfield 19	cn/com/fmsh/tsm/business/core/BusinessExtendImpl:a	Lcn/com/fmsh/util/log/FMLog;
    //   577: ifnull +43 -> 620
    //   580: aload_0
    //   581: getfield 19	cn/com/fmsh/tsm/business/core/BusinessExtendImpl:a	Lcn/com/fmsh/util/log/FMLog;
    //   584: aload_0
    //   585: getfield 29	cn/com/fmsh/tsm/business/core/BusinessExtendImpl:b	Ljava/lang/String;
    //   588: new 71	java/lang/StringBuilder
    //   591: dup
    //   592: aload 4
    //   594: invokestatic 77	java/lang/String:valueOf	(Ljava/lang/Object;)Ljava/lang/String;
    //   597: invokespecial 80	java/lang/StringBuilder:<init>	(Ljava/lang/String;)V
    //   600: iconst_4
    //   601: bipush 58
    //   603: ldc_w 402
    //   606: invokestatic 122	cn/com/fmsh/util/FM_Utils:copyValueOf	(IILjava/lang/String;)Ljava/lang/String;
    //   609: invokevirtual 92	java/lang/StringBuilder:append	(Ljava/lang/String;)Ljava/lang/StringBuilder;
    //   612: invokevirtual 95	java/lang/StringBuilder:toString	()Ljava/lang/String;
    //   615: invokeinterface 98 3 0
    //   620: new 45	cn/com/fmsh/tsm/business/exception/BusinessException
    //   623: dup
    //   624: new 71	java/lang/StringBuilder
    //   627: dup
    //   628: aload 4
    //   630: invokestatic 77	java/lang/String:valueOf	(Ljava/lang/Object;)Ljava/lang/String;
    //   633: invokespecial 80	java/lang/StringBuilder:<init>	(Ljava/lang/String;)V
    //   636: ldc_w 404
    //   639: sipush 176
    //   642: bipush 7
    //   644: invokestatic 316	cn/com/fmsh/util/Util4Java:toString	(Ljava/lang/String;II)Ljava/lang/String;
    //   647: invokevirtual 92	java/lang/StringBuilder:append	(Ljava/lang/String;)Ljava/lang/StringBuilder;
    //   650: invokevirtual 95	java/lang/StringBuilder:toString	()Ljava/lang/String;
    //   653: getstatic 127	cn/com/fmsh/tsm/business/exception/BusinessException$ErrorMessage:local_message_load_config_fail	Lcn/com/fmsh/tsm/business/exception/BusinessException$ErrorMessage;
    //   656: invokespecial 115	cn/com/fmsh/tsm/business/exception/BusinessException:<init>	(Ljava/lang/String;Lcn/com/fmsh/tsm/business/exception/BusinessException$ErrorMessage;)V
    //   659: athrow
    //   660: iload_3
    //   661: ifge -92 -> 569
    //   664: aload_0
    //   665: getfield 19	cn/com/fmsh/tsm/business/core/BusinessExtendImpl:a	Lcn/com/fmsh/util/log/FMLog;
    //   668: ifnull +45 -> 713
    //   671: aload_0
    //   672: getfield 19	cn/com/fmsh/tsm/business/core/BusinessExtendImpl:a	Lcn/com/fmsh/util/log/FMLog;
    //   675: aload_0
    //   676: getfield 29	cn/com/fmsh/tsm/business/core/BusinessExtendImpl:b	Ljava/lang/String;
    //   679: new 71	java/lang/StringBuilder
    //   682: dup
    //   683: aload 4
    //   685: invokestatic 77	java/lang/String:valueOf	(Ljava/lang/Object;)Ljava/lang/String;
    //   688: invokespecial 80	java/lang/StringBuilder:<init>	(Ljava/lang/String;)V
    //   691: ldc_w 406
    //   694: sipush 286
    //   697: bipush 6
    //   699: invokestatic 316	cn/com/fmsh/util/Util4Java:toString	(Ljava/lang/String;II)Ljava/lang/String;
    //   702: invokevirtual 92	java/lang/StringBuilder:append	(Ljava/lang/String;)Ljava/lang/StringBuilder;
    //   705: invokevirtual 95	java/lang/StringBuilder:toString	()Ljava/lang/String;
    //   708: invokeinterface 98 3 0
    //   713: new 45	cn/com/fmsh/tsm/business/exception/BusinessException
    //   716: dup
    //   717: new 71	java/lang/StringBuilder
    //   720: dup
    //   721: aload 4
    //   723: invokestatic 77	java/lang/String:valueOf	(Ljava/lang/Object;)Ljava/lang/String;
    //   726: invokespecial 80	java/lang/StringBuilder:<init>	(Ljava/lang/String;)V
    //   729: ldc_w 408
    //   732: sipush 158
    //   735: bipush 82
    //   737: invokestatic 106	cn/com/fmsh/util/FM_Bytes:startsWith	(Ljava/lang/String;II)Ljava/lang/String;
    //   740: invokevirtual 92	java/lang/StringBuilder:append	(Ljava/lang/String;)Ljava/lang/StringBuilder;
    //   743: invokevirtual 95	java/lang/StringBuilder:toString	()Ljava/lang/String;
    //   746: getstatic 127	cn/com/fmsh/tsm/business/exception/BusinessException$ErrorMessage:local_message_load_config_fail	Lcn/com/fmsh/tsm/business/exception/BusinessException$ErrorMessage;
    //   749: invokespecial 115	cn/com/fmsh/tsm/business/exception/BusinessException:<init>	(Ljava/lang/String;Lcn/com/fmsh/tsm/business/exception/BusinessException$ErrorMessage;)V
    //   752: athrow
    //   753: aload 20
    //   755: invokeinterface 412 1 0
    //   760: astore 21
    //   762: aload 21
    //   764: ifnull +10 -> 774
    //   767: aload 21
    //   769: arraylength
    //   770: iconst_1
    //   771: if_icmpge +252 -> 1023
    //   774: aload_0
    //   775: getfield 19	cn/com/fmsh/tsm/business/core/BusinessExtendImpl:a	Lcn/com/fmsh/util/log/FMLog;
    //   778: ifnull -312 -> 466
    //   781: aload_0
    //   782: getfield 19	cn/com/fmsh/tsm/business/core/BusinessExtendImpl:a	Lcn/com/fmsh/util/log/FMLog;
    //   785: aload_0
    //   786: getfield 29	cn/com/fmsh/tsm/business/core/BusinessExtendImpl:b	Ljava/lang/String;
    //   789: new 71	java/lang/StringBuilder
    //   792: dup
    //   793: aload 4
    //   795: invokestatic 77	java/lang/String:valueOf	(Ljava/lang/Object;)Ljava/lang/String;
    //   798: invokespecial 80	java/lang/StringBuilder:<init>	(Ljava/lang/String;)V
    //   801: ldc_w 414
    //   804: iconst_5
    //   805: invokestatic 55	cn/com/fmsh/util/FM_Long:concat	(Ljava/lang/String;I)Ljava/lang/String;
    //   808: invokevirtual 92	java/lang/StringBuilder:append	(Ljava/lang/String;)Ljava/lang/StringBuilder;
    //   811: invokevirtual 95	java/lang/StringBuilder:toString	()Ljava/lang/String;
    //   814: invokeinterface 98 3 0
    //   819: goto -353 -> 466
    //   822: aload_0
    //   823: getfield 31	cn/com/fmsh/tsm/business/core/BusinessExtendImpl:c	Lcn/com/fmsh/tsm/business/core/CardBusinessBasic;
    //   826: sipush 1151
    //   829: invokevirtual 153	cn/com/fmsh/tsm/business/core/CardBusinessBasic:getServer4Business	(I)Ljava/lang/String;
    //   832: astore 6
    //   834: aload 6
    //   836: ifnonnull +242 -> 1078
    //   839: aload_0
    //   840: getfield 19	cn/com/fmsh/tsm/business/core/BusinessExtendImpl:a	Lcn/com/fmsh/util/log/FMLog;
    //   843: ifnull +43 -> 886
    //   846: aload_0
    //   847: getfield 19	cn/com/fmsh/tsm/business/core/BusinessExtendImpl:a	Lcn/com/fmsh/util/log/FMLog;
    //   850: aload_0
    //   851: getfield 29	cn/com/fmsh/tsm/business/core/BusinessExtendImpl:b	Ljava/lang/String;
    //   854: new 71	java/lang/StringBuilder
    //   857: dup
    //   858: aload 4
    //   860: invokestatic 77	java/lang/String:valueOf	(Ljava/lang/Object;)Ljava/lang/String;
    //   863: invokespecial 80	java/lang/StringBuilder:<init>	(Ljava/lang/String;)V
    //   866: iconst_5
    //   867: bipush 108
    //   869: ldc_w 416
    //   872: invokestatic 122	cn/com/fmsh/util/FM_Utils:copyValueOf	(IILjava/lang/String;)Ljava/lang/String;
    //   875: invokevirtual 92	java/lang/StringBuilder:append	(Ljava/lang/String;)Ljava/lang/StringBuilder;
    //   878: invokevirtual 95	java/lang/StringBuilder:toString	()Ljava/lang/String;
    //   881: invokeinterface 98 3 0
    //   886: new 45	cn/com/fmsh/tsm/business/exception/BusinessException
    //   889: dup
    //   890: new 71	java/lang/StringBuilder
    //   893: dup
    //   894: aload 4
    //   896: invokestatic 77	java/lang/String:valueOf	(Ljava/lang/Object;)Ljava/lang/String;
    //   899: invokespecial 80	java/lang/StringBuilder:<init>	(Ljava/lang/String;)V
    //   902: iconst_3
    //   903: bipush 97
    //   905: ldc_w 418
    //   908: invokestatic 88	cn/com/fmsh/FM_Exception:getChars	(IILjava/lang/String;)Ljava/lang/String;
    //   911: invokevirtual 92	java/lang/StringBuilder:append	(Ljava/lang/String;)Ljava/lang/StringBuilder;
    //   914: invokevirtual 95	java/lang/StringBuilder:toString	()Ljava/lang/String;
    //   917: getstatic 168	cn/com/fmsh/tsm/business/exception/BusinessException$ErrorMessage:local_app_query_server_fail	Lcn/com/fmsh/tsm/business/exception/BusinessException$ErrorMessage;
    //   920: invokespecial 115	cn/com/fmsh/tsm/business/exception/BusinessException:<init>	(Ljava/lang/String;Lcn/com/fmsh/tsm/business/exception/BusinessException$ErrorMessage;)V
    //   923: athrow
    //   924: aload_0
    //   925: getfield 31	cn/com/fmsh/tsm/business/core/BusinessExtendImpl:c	Lcn/com/fmsh/tsm/business/core/CardBusinessBasic;
    //   928: invokevirtual 172	cn/com/fmsh/tsm/business/core/CardBusinessBasic:getMessageHandler	()Lcn/com/fmsh/communication/message/IMessageHandler;
    //   931: astore 5
    //   933: aload 5
    //   935: ifnonnull -275 -> 660
    //   938: aload_0
    //   939: getfield 19	cn/com/fmsh/tsm/business/core/BusinessExtendImpl:a	Lcn/com/fmsh/util/log/FMLog;
    //   942: ifnull +43 -> 985
    //   945: aload_0
    //   946: getfield 19	cn/com/fmsh/tsm/business/core/BusinessExtendImpl:a	Lcn/com/fmsh/util/log/FMLog;
    //   949: aload_0
    //   950: getfield 29	cn/com/fmsh/tsm/business/core/BusinessExtendImpl:b	Ljava/lang/String;
    //   953: new 71	java/lang/StringBuilder
    //   956: dup
    //   957: aload 4
    //   959: invokestatic 77	java/lang/String:valueOf	(Ljava/lang/Object;)Ljava/lang/String;
    //   962: invokespecial 80	java/lang/StringBuilder:<init>	(Ljava/lang/String;)V
    //   965: sipush 288
    //   968: ldc_w 420
    //   971: invokestatic 63	cn/com/fmsh/util/FM_Int:lastIndexOf	(ILjava/lang/String;)Ljava/lang/String;
    //   974: invokevirtual 92	java/lang/StringBuilder:append	(Ljava/lang/String;)Ljava/lang/StringBuilder;
    //   977: invokevirtual 95	java/lang/StringBuilder:toString	()Ljava/lang/String;
    //   980: invokeinterface 98 3 0
    //   985: new 45	cn/com/fmsh/tsm/business/exception/BusinessException
    //   988: dup
    //   989: new 71	java/lang/StringBuilder
    //   992: dup
    //   993: aload 4
    //   995: invokestatic 77	java/lang/String:valueOf	(Ljava/lang/Object;)Ljava/lang/String;
    //   998: invokespecial 80	java/lang/StringBuilder:<init>	(Ljava/lang/String;)V
    //   1001: iconst_5
    //   1002: bipush 125
    //   1004: ldc_w 422
    //   1007: invokestatic 88	cn/com/fmsh/FM_Exception:getChars	(IILjava/lang/String;)Ljava/lang/String;
    //   1010: invokevirtual 92	java/lang/StringBuilder:append	(Ljava/lang/String;)Ljava/lang/StringBuilder;
    //   1013: invokevirtual 95	java/lang/StringBuilder:toString	()Ljava/lang/String;
    //   1016: getstatic 127	cn/com/fmsh/tsm/business/exception/BusinessException$ErrorMessage:local_message_load_config_fail	Lcn/com/fmsh/tsm/business/exception/BusinessException$ErrorMessage;
    //   1019: invokespecial 115	cn/com/fmsh/tsm/business/exception/BusinessException:<init>	(Ljava/lang/String;Lcn/com/fmsh/tsm/business/exception/BusinessException$ErrorMessage;)V
    //   1022: athrow
    //   1023: aload 21
    //   1025: arraylength
    //   1026: istore 22
    //   1028: iconst_0
    //   1029: istore 23
    //   1031: iload 23
    //   1033: iload 22
    //   1035: if_icmpge -569 -> 466
    //   1038: aload 21
    //   1040: iload 23
    //   1042: aaload
    //   1043: astore 24
    //   1045: aload 24
    //   1047: ifnull +25 -> 1072
    //   1050: aload 24
    //   1052: invokestatic 365	cn/com/fmsh/tsm/business/bean/ElectronicTakeUp:fromTag	(Lcn/com/fmsh/communication/message/ITag;)Lcn/com/fmsh/tsm/business/bean/ElectronicTakeUp;
    //   1055: astore 25
    //   1057: aload 25
    //   1059: ifnull +13 -> 1072
    //   1062: aload 18
    //   1064: aload 25
    //   1066: invokeinterface 428 2 0
    //   1071: pop
    //   1072: iinc 23 1
    //   1075: goto -44 -> 1031
    //   1078: aload_0
    //   1079: getfield 31	cn/com/fmsh/tsm/business/core/BusinessExtendImpl:c	Lcn/com/fmsh/tsm/business/core/CardBusinessBasic;
    //   1082: aload 4
    //   1084: aload 6
    //   1086: invokevirtual 218	cn/com/fmsh/tsm/business/core/CardBusinessBasic:businessReady	(Ljava/lang/String;Ljava/lang/String;)V
    //   1089: aconst_null
    //   1090: astore 7
    //   1092: aload 5
    //   1094: sipush 4641
    //   1097: invokeinterface 224 2 0
    //   1102: astore 8
    //   1104: aload_1
    //   1105: ifnull +38 -> 1143
    //   1108: aload_1
    //   1109: arraylength
    //   1110: ifle +33 -> 1143
    //   1113: aload 5
    //   1115: bipush 113
    //   1117: invokeinterface 228 2 0
    //   1122: astore 28
    //   1124: aload 28
    //   1126: aload_1
    //   1127: invokeinterface 233 2 0
    //   1132: pop
    //   1133: aload 8
    //   1135: aload 28
    //   1137: invokeinterface 239 2 0
    //   1142: pop
    //   1143: aload 5
    //   1145: bipush 121
    //   1147: invokeinterface 228 2 0
    //   1152: astore 9
    //   1154: aload 9
    //   1156: iload_2
    //   1157: invokeinterface 308 2 0
    //   1162: pop
    //   1163: aload 8
    //   1165: aload 9
    //   1167: invokeinterface 239 2 0
    //   1172: pop
    //   1173: aload 5
    //   1175: bipush 38
    //   1177: invokeinterface 228 2 0
    //   1182: astore 12
    //   1184: aload 12
    //   1186: iload_3
    //   1187: invokeinterface 308 2 0
    //   1192: pop
    //   1193: aload 8
    //   1195: aload 12
    //   1197: invokeinterface 239 2 0
    //   1202: pop
    //   1203: aload 8
    //   1205: invokeinterface 243 1 0
    //   1210: astore 15
    //   1212: aload 15
    //   1214: astore 7
    //   1216: goto -970 -> 246
    //
    // Exception table:
    //   from	to	target	type
    //   1108	1212	150	cn/com/fmsh/communication/message/exception/FMCommunicationMessageException
    //   386	466	469	cn/com/fmsh/communication/message/exception/FMCommunicationMessageException
    //   753	819	469	cn/com/fmsh/communication/message/exception/FMCommunicationMessageException
    //   1023	1072	469	cn/com/fmsh/communication/message/exception/FMCommunicationMessageException
  }

  // ERROR //
  public cn.com.fmsh.tsm.business.bean.MainOrder useElectronicTakeUp(byte[] paramArrayOfByte1, byte[] paramArrayOfByte2, byte[] paramArrayOfByte3, cn.com.fmsh.tsm.business.enums.EnumCardIoType paramEnumCardIoType)
    throws cn.com.fmsh.tsm.business.exception.BusinessException
  {
    // Byte code:
    //   0: iconst_2
    //   1: ldc_w 432
    //   4: invokestatic 137	cn/com/fmsh/util/CRCUtil:valueOf	(ILjava/lang/String;)Ljava/lang/String;
    //   7: astore 5
    //   9: aload_0
    //   10: getfield 19	cn/com/fmsh/tsm/business/core/BusinessExtendImpl:a	Lcn/com/fmsh/util/log/FMLog;
    //   13: ifnonnull +13 -> 26
    //   16: aload_0
    //   17: invokestatic 37	cn/com/fmsh/util/log/LogFactory:getInstance	()Lcn/com/fmsh/util/log/LogFactory;
    //   20: invokevirtual 41	cn/com/fmsh/util/log/LogFactory:getLog	()Lcn/com/fmsh/util/log/FMLog;
    //   23: putfield 19	cn/com/fmsh/tsm/business/core/BusinessExtendImpl:a	Lcn/com/fmsh/util/log/FMLog;
    //   26: aload_0
    //   27: getfield 19	cn/com/fmsh/tsm/business/core/BusinessExtendImpl:a	Lcn/com/fmsh/util/log/FMLog;
    //   30: ifnull +23 -> 53
    //   33: aload_0
    //   34: getfield 19	cn/com/fmsh/tsm/business/core/BusinessExtendImpl:a	Lcn/com/fmsh/util/log/FMLog;
    //   37: aload_0
    //   38: getfield 29	cn/com/fmsh/tsm/business/core/BusinessExtendImpl:b	Ljava/lang/String;
    //   41: ldc_w 434
    //   44: iconst_4
    //   45: invokestatic 165	cn/com/fmsh/util/FM_CN:subSequence	(Ljava/lang/String;I)Ljava/lang/String;
    //   48: invokeinterface 69 3 0
    //   53: aload_0
    //   54: getfield 31	cn/com/fmsh/tsm/business/core/BusinessExtendImpl:c	Lcn/com/fmsh/tsm/business/core/CardBusinessBasic;
    //   57: ifnonnull +826 -> 883
    //   60: aload_0
    //   61: getfield 19	cn/com/fmsh/tsm/business/core/BusinessExtendImpl:a	Lcn/com/fmsh/util/log/FMLog;
    //   64: ifnull +43 -> 107
    //   67: aload_0
    //   68: getfield 19	cn/com/fmsh/tsm/business/core/BusinessExtendImpl:a	Lcn/com/fmsh/util/log/FMLog;
    //   71: aload_0
    //   72: getfield 29	cn/com/fmsh/tsm/business/core/BusinessExtendImpl:b	Ljava/lang/String;
    //   75: new 71	java/lang/StringBuilder
    //   78: dup
    //   79: aload 5
    //   81: invokestatic 77	java/lang/String:valueOf	(Ljava/lang/Object;)Ljava/lang/String;
    //   84: invokespecial 80	java/lang/StringBuilder:<init>	(Ljava/lang/String;)V
    //   87: sipush 278
    //   90: ldc_w 436
    //   93: invokestatic 63	cn/com/fmsh/util/FM_Int:lastIndexOf	(ILjava/lang/String;)Ljava/lang/String;
    //   96: invokevirtual 92	java/lang/StringBuilder:append	(Ljava/lang/String;)Ljava/lang/StringBuilder;
    //   99: invokevirtual 95	java/lang/StringBuilder:toString	()Ljava/lang/String;
    //   102: invokeinterface 98 3 0
    //   107: new 45	cn/com/fmsh/tsm/business/exception/BusinessException
    //   110: dup
    //   111: new 71	java/lang/StringBuilder
    //   114: dup
    //   115: aload 5
    //   117: invokestatic 77	java/lang/String:valueOf	(Ljava/lang/Object;)Ljava/lang/String;
    //   120: invokespecial 80	java/lang/StringBuilder:<init>	(Ljava/lang/String;)V
    //   123: bipush 6
    //   125: ldc_w 438
    //   128: invokestatic 63	cn/com/fmsh/util/FM_Int:lastIndexOf	(ILjava/lang/String;)Ljava/lang/String;
    //   131: invokevirtual 92	java/lang/StringBuilder:append	(Ljava/lang/String;)Ljava/lang/StringBuilder;
    //   134: invokevirtual 95	java/lang/StringBuilder:toString	()Ljava/lang/String;
    //   137: getstatic 112	cn/com/fmsh/tsm/business/exception/BusinessException$ErrorMessage:local_business_init_fail	Lcn/com/fmsh/tsm/business/exception/BusinessException$ErrorMessage;
    //   140: invokespecial 115	cn/com/fmsh/tsm/business/exception/BusinessException:<init>	(Ljava/lang/String;Lcn/com/fmsh/tsm/business/exception/BusinessException$ErrorMessage;)V
    //   143: athrow
    //   144: aload_3
    //   145: ifnull +9 -> 154
    //   148: aload_3
    //   149: arraylength
    //   150: iconst_1
    //   151: if_icmpge +922 -> 1073
    //   154: aload_0
    //   155: getfield 19	cn/com/fmsh/tsm/business/core/BusinessExtendImpl:a	Lcn/com/fmsh/util/log/FMLog;
    //   158: ifnull +43 -> 201
    //   161: aload_0
    //   162: getfield 19	cn/com/fmsh/tsm/business/core/BusinessExtendImpl:a	Lcn/com/fmsh/util/log/FMLog;
    //   165: aload_0
    //   166: getfield 29	cn/com/fmsh/tsm/business/core/BusinessExtendImpl:b	Ljava/lang/String;
    //   169: new 71	java/lang/StringBuilder
    //   172: dup
    //   173: aload 5
    //   175: invokestatic 77	java/lang/String:valueOf	(Ljava/lang/Object;)Ljava/lang/String;
    //   178: invokespecial 80	java/lang/StringBuilder:<init>	(Ljava/lang/String;)V
    //   181: iconst_3
    //   182: bipush 96
    //   184: ldc_w 440
    //   187: invokestatic 88	cn/com/fmsh/FM_Exception:getChars	(IILjava/lang/String;)Ljava/lang/String;
    //   190: invokevirtual 92	java/lang/StringBuilder:append	(Ljava/lang/String;)Ljava/lang/StringBuilder;
    //   193: invokevirtual 95	java/lang/StringBuilder:toString	()Ljava/lang/String;
    //   196: invokeinterface 98 3 0
    //   201: new 45	cn/com/fmsh/tsm/business/exception/BusinessException
    //   204: dup
    //   205: new 71	java/lang/StringBuilder
    //   208: dup
    //   209: aload 5
    //   211: invokestatic 77	java/lang/String:valueOf	(Ljava/lang/Object;)Ljava/lang/String;
    //   214: invokespecial 80	java/lang/StringBuilder:<init>	(Ljava/lang/String;)V
    //   217: iconst_1
    //   218: ldc_w 442
    //   221: invokestatic 137	cn/com/fmsh/util/CRCUtil:valueOf	(ILjava/lang/String;)Ljava/lang/String;
    //   224: invokevirtual 92	java/lang/StringBuilder:append	(Ljava/lang/String;)Ljava/lang/StringBuilder;
    //   227: invokevirtual 95	java/lang/StringBuilder:toString	()Ljava/lang/String;
    //   230: getstatic 127	cn/com/fmsh/tsm/business/exception/BusinessException$ErrorMessage:local_message_load_config_fail	Lcn/com/fmsh/tsm/business/exception/BusinessException$ErrorMessage;
    //   233: invokespecial 115	cn/com/fmsh/tsm/business/exception/BusinessException:<init>	(Ljava/lang/String;Lcn/com/fmsh/tsm/business/exception/BusinessException$ErrorMessage;)V
    //   236: athrow
    //   237: astore 29
    //   239: aload_0
    //   240: getfield 19	cn/com/fmsh/tsm/business/core/BusinessExtendImpl:a	Lcn/com/fmsh/util/log/FMLog;
    //   243: ifnull +51 -> 294
    //   246: aload_0
    //   247: getfield 19	cn/com/fmsh/tsm/business/core/BusinessExtendImpl:a	Lcn/com/fmsh/util/log/FMLog;
    //   250: aload_0
    //   251: getfield 29	cn/com/fmsh/tsm/business/core/BusinessExtendImpl:b	Ljava/lang/String;
    //   254: new 71	java/lang/StringBuilder
    //   257: dup
    //   258: aload 5
    //   260: invokestatic 77	java/lang/String:valueOf	(Ljava/lang/Object;)Ljava/lang/String;
    //   263: invokespecial 80	java/lang/StringBuilder:<init>	(Ljava/lang/String;)V
    //   266: sipush 224
    //   269: ldc_w 444
    //   272: invokestatic 63	cn/com/fmsh/util/FM_Int:lastIndexOf	(ILjava/lang/String;)Ljava/lang/String;
    //   275: invokevirtual 92	java/lang/StringBuilder:append	(Ljava/lang/String;)Ljava/lang/StringBuilder;
    //   278: aload 29
    //   280: invokestatic 184	cn/com/fmsh/util/Util4Java:getExceptionInfo	(Ljava/lang/Exception;)Ljava/lang/String;
    //   283: invokevirtual 92	java/lang/StringBuilder:append	(Ljava/lang/String;)Ljava/lang/StringBuilder;
    //   286: invokevirtual 95	java/lang/StringBuilder:toString	()Ljava/lang/String;
    //   289: invokeinterface 98 3 0
    //   294: aload_0
    //   295: getfield 31	cn/com/fmsh/tsm/business/core/BusinessExtendImpl:c	Lcn/com/fmsh/tsm/business/core/CardBusinessBasic;
    //   298: new 71	java/lang/StringBuilder
    //   301: dup
    //   302: aload 5
    //   304: invokestatic 77	java/lang/String:valueOf	(Ljava/lang/Object;)Ljava/lang/String;
    //   307: invokespecial 80	java/lang/StringBuilder:<init>	(Ljava/lang/String;)V
    //   310: ldc_w 446
    //   313: iconst_5
    //   314: invokestatic 165	cn/com/fmsh/util/FM_CN:subSequence	(Ljava/lang/String;I)Ljava/lang/String;
    //   317: invokevirtual 92	java/lang/StringBuilder:append	(Ljava/lang/String;)Ljava/lang/StringBuilder;
    //   320: invokevirtual 95	java/lang/StringBuilder:toString	()Ljava/lang/String;
    //   323: getstatic 189	cn/com/fmsh/tsm/business/exception/BusinessException$ErrorMessage:local_message_message_handle_exception	Lcn/com/fmsh/tsm/business/exception/BusinessException$ErrorMessage;
    //   326: iconst_0
    //   327: invokevirtual 193	cn/com/fmsh/tsm/business/core/CardBusinessBasic:throwExceptionAndClose	(Ljava/lang/String;Lcn/com/fmsh/tsm/business/exception/BusinessException$ErrorMessage;Z)V
    //   330: aload_0
    //   331: getfield 31	cn/com/fmsh/tsm/business/core/BusinessExtendImpl:c	Lcn/com/fmsh/tsm/business/core/CardBusinessBasic;
    //   334: aload 8
    //   336: aload 5
    //   338: iconst_0
    //   339: aload 7
    //   341: invokevirtual 197	cn/com/fmsh/tsm/business/core/CardBusinessBasic:interaction	([BLjava/lang/String;ZLjava/lang/String;)[B
    //   344: astore 23
    //   346: iconst_2
    //   347: newarray byte
    //   349: astore 24
    //   351: aload 23
    //   353: iconst_0
    //   354: aload 24
    //   356: iconst_0
    //   357: aload 24
    //   359: arraylength
    //   360: invokestatic 203	java/lang/System:arraycopy	(Ljava/lang/Object;ILjava/lang/Object;II)V
    //   363: getstatic 209	cn/com/fmsh/tsm/business/constants/Constants$RespCodeonse4Platform:SUCESS	[B
    //   366: aload 24
    //   368: invokestatic 215	java/util/Arrays:equals	([B[B)Z
    //   371: ifne +101 -> 472
    //   374: aload_0
    //   375: getfield 19	cn/com/fmsh/tsm/business/core/BusinessExtendImpl:a	Lcn/com/fmsh/util/log/FMLog;
    //   378: ifnull +51 -> 429
    //   381: aload_0
    //   382: getfield 19	cn/com/fmsh/tsm/business/core/BusinessExtendImpl:a	Lcn/com/fmsh/util/log/FMLog;
    //   385: aload_0
    //   386: getfield 29	cn/com/fmsh/tsm/business/core/BusinessExtendImpl:b	Ljava/lang/String;
    //   389: new 71	java/lang/StringBuilder
    //   392: dup
    //   393: aload 5
    //   395: invokestatic 77	java/lang/String:valueOf	(Ljava/lang/Object;)Ljava/lang/String;
    //   398: invokespecial 80	java/lang/StringBuilder:<init>	(Ljava/lang/String;)V
    //   401: ldc_w 448
    //   404: iconst_5
    //   405: bipush 40
    //   407: invokestatic 160	cn/com/fmsh/util/BCCUtil:endsWith	(Ljava/lang/String;II)Ljava/lang/String;
    //   410: invokevirtual 92	java/lang/StringBuilder:append	(Ljava/lang/String;)Ljava/lang/StringBuilder;
    //   413: aload 23
    //   415: invokestatic 141	cn/com/fmsh/util/FM_Bytes:bytesToHexString	([B)Ljava/lang/String;
    //   418: invokevirtual 92	java/lang/StringBuilder:append	(Ljava/lang/String;)Ljava/lang/StringBuilder;
    //   421: invokevirtual 95	java/lang/StringBuilder:toString	()Ljava/lang/String;
    //   424: invokeinterface 266 3 0
    //   429: aload_0
    //   430: getfield 31	cn/com/fmsh/tsm/business/core/BusinessExtendImpl:c	Lcn/com/fmsh/tsm/business/core/CardBusinessBasic;
    //   433: new 71	java/lang/StringBuilder
    //   436: dup
    //   437: aload 5
    //   439: invokestatic 77	java/lang/String:valueOf	(Ljava/lang/Object;)Ljava/lang/String;
    //   442: invokespecial 80	java/lang/StringBuilder:<init>	(Ljava/lang/String;)V
    //   445: iconst_1
    //   446: bipush 72
    //   448: ldc_w 450
    //   451: invokestatic 88	cn/com/fmsh/FM_Exception:getChars	(IILjava/lang/String;)Ljava/lang/String;
    //   454: invokevirtual 92	java/lang/StringBuilder:append	(Ljava/lang/String;)Ljava/lang/StringBuilder;
    //   457: invokevirtual 95	java/lang/StringBuilder:toString	()Ljava/lang/String;
    //   460: aload 24
    //   462: invokestatic 141	cn/com/fmsh/util/FM_Bytes:bytesToHexString	([B)Ljava/lang/String;
    //   465: invokestatic 391	cn/com/fmsh/tsm/business/exception/BusinessException$ErrorMessage:instance	(Ljava/lang/String;)Lcn/com/fmsh/tsm/business/exception/BusinessException$ErrorMessage;
    //   468: iconst_0
    //   469: invokevirtual 193	cn/com/fmsh/tsm/business/core/CardBusinessBasic:throwExceptionAndClose	(Ljava/lang/String;Lcn/com/fmsh/tsm/business/exception/BusinessException$ErrorMessage;Z)V
    //   472: aconst_null
    //   473: astore 25
    //   475: aload 6
    //   477: sipush 1112
    //   480: aload 23
    //   482: iconst_2
    //   483: aload 23
    //   485: arraylength
    //   486: invokestatic 278	java/util/Arrays:copyOfRange	([BII)[B
    //   489: invokeinterface 281 3 0
    //   494: bipush 96
    //   496: invokeinterface 285 2 0
    //   501: astore 27
    //   503: aload 27
    //   505: ifnull +14 -> 519
    //   508: aload 27
    //   510: invokestatic 455	cn/com/fmsh/tsm/business/bean/MainOrder:fromTag	(Lcn/com/fmsh/communication/message/ITag;)Lcn/com/fmsh/tsm/business/bean/MainOrder;
    //   513: astore 28
    //   515: aload 28
    //   517: astore 25
    //   519: aload 25
    //   521: areturn
    //   522: aload_0
    //   523: getfield 31	cn/com/fmsh/tsm/business/core/BusinessExtendImpl:c	Lcn/com/fmsh/tsm/business/core/CardBusinessBasic;
    //   526: aload 5
    //   528: aload 7
    //   530: invokevirtual 218	cn/com/fmsh/tsm/business/core/CardBusinessBasic:businessReady	(Ljava/lang/String;Ljava/lang/String;)V
    //   533: aconst_null
    //   534: astore 8
    //   536: aload 6
    //   538: sipush 4621
    //   541: invokeinterface 224 2 0
    //   546: astore 9
    //   548: aload 6
    //   550: bipush 112
    //   552: invokeinterface 228 2 0
    //   557: astore 10
    //   559: aload 10
    //   561: aload_1
    //   562: invokeinterface 233 2 0
    //   567: pop
    //   568: aload 9
    //   570: aload 10
    //   572: invokeinterface 239 2 0
    //   577: pop
    //   578: aload 6
    //   580: bipush 113
    //   582: invokeinterface 228 2 0
    //   587: astore 13
    //   589: aload 13
    //   591: aload_2
    //   592: invokeinterface 233 2 0
    //   597: pop
    //   598: aload 9
    //   600: aload 13
    //   602: invokeinterface 239 2 0
    //   607: pop
    //   608: aload 6
    //   610: bipush 15
    //   612: invokeinterface 228 2 0
    //   617: astore 16
    //   619: aload 16
    //   621: aload_3
    //   622: invokestatic 141	cn/com/fmsh/util/FM_Bytes:bytesToHexString	([B)Ljava/lang/String;
    //   625: invokeinterface 305 2 0
    //   630: pop
    //   631: aload 9
    //   633: aload 16
    //   635: invokeinterface 239 2 0
    //   640: pop
    //   641: aload 6
    //   643: bipush 47
    //   645: invokeinterface 228 2 0
    //   650: astore 19
    //   652: aload 19
    //   654: aload 4
    //   656: invokevirtual 461	cn/com/fmsh/tsm/business/enums/EnumCardIoType:getId	()I
    //   659: invokeinterface 308 2 0
    //   664: pop
    //   665: aload 9
    //   667: aload 19
    //   669: invokeinterface 239 2 0
    //   674: pop
    //   675: aload 9
    //   677: invokeinterface 243 1 0
    //   682: astore 22
    //   684: aload 22
    //   686: astore 8
    //   688: goto -358 -> 330
    //   691: aload_2
    //   692: ifnonnull -548 -> 144
    //   695: aload_0
    //   696: getfield 19	cn/com/fmsh/tsm/business/core/BusinessExtendImpl:a	Lcn/com/fmsh/util/log/FMLog;
    //   699: ifnull +43 -> 742
    //   702: aload_0
    //   703: getfield 19	cn/com/fmsh/tsm/business/core/BusinessExtendImpl:a	Lcn/com/fmsh/util/log/FMLog;
    //   706: aload_0
    //   707: getfield 29	cn/com/fmsh/tsm/business/core/BusinessExtendImpl:b	Ljava/lang/String;
    //   710: new 71	java/lang/StringBuilder
    //   713: dup
    //   714: aload 5
    //   716: invokestatic 77	java/lang/String:valueOf	(Ljava/lang/Object;)Ljava/lang/String;
    //   719: invokespecial 80	java/lang/StringBuilder:<init>	(Ljava/lang/String;)V
    //   722: ldc_w 463
    //   725: iconst_4
    //   726: bipush 104
    //   728: invokestatic 106	cn/com/fmsh/util/FM_Bytes:startsWith	(Ljava/lang/String;II)Ljava/lang/String;
    //   731: invokevirtual 92	java/lang/StringBuilder:append	(Ljava/lang/String;)Ljava/lang/StringBuilder;
    //   734: invokevirtual 95	java/lang/StringBuilder:toString	()Ljava/lang/String;
    //   737: invokeinterface 98 3 0
    //   742: new 45	cn/com/fmsh/tsm/business/exception/BusinessException
    //   745: dup
    //   746: new 71	java/lang/StringBuilder
    //   749: dup
    //   750: aload 5
    //   752: invokestatic 77	java/lang/String:valueOf	(Ljava/lang/Object;)Ljava/lang/String;
    //   755: invokespecial 80	java/lang/StringBuilder:<init>	(Ljava/lang/String;)V
    //   758: ldc_w 465
    //   761: bipush 122
    //   763: bipush 100
    //   765: invokestatic 160	cn/com/fmsh/util/BCCUtil:endsWith	(Ljava/lang/String;II)Ljava/lang/String;
    //   768: invokevirtual 92	java/lang/StringBuilder:append	(Ljava/lang/String;)Ljava/lang/StringBuilder;
    //   771: invokevirtual 95	java/lang/StringBuilder:toString	()Ljava/lang/String;
    //   774: getstatic 127	cn/com/fmsh/tsm/business/exception/BusinessException$ErrorMessage:local_message_load_config_fail	Lcn/com/fmsh/tsm/business/exception/BusinessException$ErrorMessage;
    //   777: invokespecial 115	cn/com/fmsh/tsm/business/exception/BusinessException:<init>	(Ljava/lang/String;Lcn/com/fmsh/tsm/business/exception/BusinessException$ErrorMessage;)V
    //   780: athrow
    //   781: astore 26
    //   783: aload_0
    //   784: getfield 19	cn/com/fmsh/tsm/business/core/BusinessExtendImpl:a	Lcn/com/fmsh/util/log/FMLog;
    //   787: ifnull +53 -> 840
    //   790: aload_0
    //   791: getfield 19	cn/com/fmsh/tsm/business/core/BusinessExtendImpl:a	Lcn/com/fmsh/util/log/FMLog;
    //   794: aload_0
    //   795: getfield 29	cn/com/fmsh/tsm/business/core/BusinessExtendImpl:b	Ljava/lang/String;
    //   798: new 71	java/lang/StringBuilder
    //   801: dup
    //   802: aload 5
    //   804: invokestatic 77	java/lang/String:valueOf	(Ljava/lang/Object;)Ljava/lang/String;
    //   807: invokespecial 80	java/lang/StringBuilder:<init>	(Ljava/lang/String;)V
    //   810: ldc_w 467
    //   813: sipush 222
    //   816: bipush 110
    //   818: invokestatic 106	cn/com/fmsh/util/FM_Bytes:startsWith	(Ljava/lang/String;II)Ljava/lang/String;
    //   821: invokevirtual 92	java/lang/StringBuilder:append	(Ljava/lang/String;)Ljava/lang/StringBuilder;
    //   824: aload 26
    //   826: invokestatic 184	cn/com/fmsh/util/Util4Java:getExceptionInfo	(Ljava/lang/Exception;)Ljava/lang/String;
    //   829: invokevirtual 92	java/lang/StringBuilder:append	(Ljava/lang/String;)Ljava/lang/StringBuilder;
    //   832: invokevirtual 95	java/lang/StringBuilder:toString	()Ljava/lang/String;
    //   835: invokeinterface 266 3 0
    //   840: aload_0
    //   841: getfield 31	cn/com/fmsh/tsm/business/core/BusinessExtendImpl:c	Lcn/com/fmsh/tsm/business/core/CardBusinessBasic;
    //   844: new 71	java/lang/StringBuilder
    //   847: dup
    //   848: aload 5
    //   850: invokestatic 77	java/lang/String:valueOf	(Ljava/lang/Object;)Ljava/lang/String;
    //   853: invokespecial 80	java/lang/StringBuilder:<init>	(Ljava/lang/String;)V
    //   856: ldc_w 469
    //   859: sipush 158
    //   862: bipush 84
    //   864: invokestatic 316	cn/com/fmsh/util/Util4Java:toString	(Ljava/lang/String;II)Ljava/lang/String;
    //   867: invokevirtual 92	java/lang/StringBuilder:append	(Ljava/lang/String;)Ljava/lang/StringBuilder;
    //   870: invokevirtual 95	java/lang/StringBuilder:toString	()Ljava/lang/String;
    //   873: getstatic 189	cn/com/fmsh/tsm/business/exception/BusinessException$ErrorMessage:local_message_message_handle_exception	Lcn/com/fmsh/tsm/business/exception/BusinessException$ErrorMessage;
    //   876: iconst_0
    //   877: invokevirtual 193	cn/com/fmsh/tsm/business/core/CardBusinessBasic:throwExceptionAndClose	(Ljava/lang/String;Lcn/com/fmsh/tsm/business/exception/BusinessException$ErrorMessage;Z)V
    //   880: goto -361 -> 519
    //   883: aload_0
    //   884: getfield 31	cn/com/fmsh/tsm/business/core/BusinessExtendImpl:c	Lcn/com/fmsh/tsm/business/core/CardBusinessBasic;
    //   887: invokevirtual 172	cn/com/fmsh/tsm/business/core/CardBusinessBasic:getMessageHandler	()Lcn/com/fmsh/communication/message/IMessageHandler;
    //   890: astore 6
    //   892: aload 6
    //   894: ifnonnull +90 -> 984
    //   897: aload_0
    //   898: getfield 19	cn/com/fmsh/tsm/business/core/BusinessExtendImpl:a	Lcn/com/fmsh/util/log/FMLog;
    //   901: ifnull +45 -> 946
    //   904: aload_0
    //   905: getfield 19	cn/com/fmsh/tsm/business/core/BusinessExtendImpl:a	Lcn/com/fmsh/util/log/FMLog;
    //   908: aload_0
    //   909: getfield 29	cn/com/fmsh/tsm/business/core/BusinessExtendImpl:b	Ljava/lang/String;
    //   912: new 71	java/lang/StringBuilder
    //   915: dup
    //   916: aload 5
    //   918: invokestatic 77	java/lang/String:valueOf	(Ljava/lang/Object;)Ljava/lang/String;
    //   921: invokespecial 80	java/lang/StringBuilder:<init>	(Ljava/lang/String;)V
    //   924: sipush 258
    //   927: bipush 90
    //   929: ldc_w 471
    //   932: invokestatic 88	cn/com/fmsh/FM_Exception:getChars	(IILjava/lang/String;)Ljava/lang/String;
    //   935: invokevirtual 92	java/lang/StringBuilder:append	(Ljava/lang/String;)Ljava/lang/StringBuilder;
    //   938: invokevirtual 95	java/lang/StringBuilder:toString	()Ljava/lang/String;
    //   941: invokeinterface 98 3 0
    //   946: new 45	cn/com/fmsh/tsm/business/exception/BusinessException
    //   949: dup
    //   950: new 71	java/lang/StringBuilder
    //   953: dup
    //   954: aload 5
    //   956: invokestatic 77	java/lang/String:valueOf	(Ljava/lang/Object;)Ljava/lang/String;
    //   959: invokespecial 80	java/lang/StringBuilder:<init>	(Ljava/lang/String;)V
    //   962: sipush 226
    //   965: ldc_w 473
    //   968: invokestatic 137	cn/com/fmsh/util/CRCUtil:valueOf	(ILjava/lang/String;)Ljava/lang/String;
    //   971: invokevirtual 92	java/lang/StringBuilder:append	(Ljava/lang/String;)Ljava/lang/StringBuilder;
    //   974: invokevirtual 95	java/lang/StringBuilder:toString	()Ljava/lang/String;
    //   977: getstatic 127	cn/com/fmsh/tsm/business/exception/BusinessException$ErrorMessage:local_message_load_config_fail	Lcn/com/fmsh/tsm/business/exception/BusinessException$ErrorMessage;
    //   980: invokespecial 115	cn/com/fmsh/tsm/business/exception/BusinessException:<init>	(Ljava/lang/String;Lcn/com/fmsh/tsm/business/exception/BusinessException$ErrorMessage;)V
    //   983: athrow
    //   984: aload_1
    //   985: ifnonnull -294 -> 691
    //   988: aload_0
    //   989: getfield 19	cn/com/fmsh/tsm/business/core/BusinessExtendImpl:a	Lcn/com/fmsh/util/log/FMLog;
    //   992: ifnull +43 -> 1035
    //   995: aload_0
    //   996: getfield 19	cn/com/fmsh/tsm/business/core/BusinessExtendImpl:a	Lcn/com/fmsh/util/log/FMLog;
    //   999: aload_0
    //   1000: getfield 29	cn/com/fmsh/tsm/business/core/BusinessExtendImpl:b	Ljava/lang/String;
    //   1003: new 71	java/lang/StringBuilder
    //   1006: dup
    //   1007: aload 5
    //   1009: invokestatic 77	java/lang/String:valueOf	(Ljava/lang/Object;)Ljava/lang/String;
    //   1012: invokespecial 80	java/lang/StringBuilder:<init>	(Ljava/lang/String;)V
    //   1015: ldc_w 475
    //   1018: iconst_5
    //   1019: bipush 87
    //   1021: invokestatic 106	cn/com/fmsh/util/FM_Bytes:startsWith	(Ljava/lang/String;II)Ljava/lang/String;
    //   1024: invokevirtual 92	java/lang/StringBuilder:append	(Ljava/lang/String;)Ljava/lang/StringBuilder;
    //   1027: invokevirtual 95	java/lang/StringBuilder:toString	()Ljava/lang/String;
    //   1030: invokeinterface 98 3 0
    //   1035: new 45	cn/com/fmsh/tsm/business/exception/BusinessException
    //   1038: dup
    //   1039: new 71	java/lang/StringBuilder
    //   1042: dup
    //   1043: aload 5
    //   1045: invokestatic 77	java/lang/String:valueOf	(Ljava/lang/Object;)Ljava/lang/String;
    //   1048: invokespecial 80	java/lang/StringBuilder:<init>	(Ljava/lang/String;)V
    //   1051: ldc_w 477
    //   1054: sipush 284
    //   1057: invokestatic 55	cn/com/fmsh/util/FM_Long:concat	(Ljava/lang/String;I)Ljava/lang/String;
    //   1060: invokevirtual 92	java/lang/StringBuilder:append	(Ljava/lang/String;)Ljava/lang/StringBuilder;
    //   1063: invokevirtual 95	java/lang/StringBuilder:toString	()Ljava/lang/String;
    //   1066: getstatic 127	cn/com/fmsh/tsm/business/exception/BusinessException$ErrorMessage:local_message_load_config_fail	Lcn/com/fmsh/tsm/business/exception/BusinessException$ErrorMessage;
    //   1069: invokespecial 115	cn/com/fmsh/tsm/business/exception/BusinessException:<init>	(Ljava/lang/String;Lcn/com/fmsh/tsm/business/exception/BusinessException$ErrorMessage;)V
    //   1072: athrow
    //   1073: aload_0
    //   1074: getfield 31	cn/com/fmsh/tsm/business/core/BusinessExtendImpl:c	Lcn/com/fmsh/tsm/business/core/CardBusinessBasic;
    //   1077: sipush 1151
    //   1080: invokevirtual 153	cn/com/fmsh/tsm/business/core/CardBusinessBasic:getServer4Business	(I)Ljava/lang/String;
    //   1083: astore 7
    //   1085: aload 7
    //   1087: ifnonnull -565 -> 522
    //   1090: aload_0
    //   1091: getfield 19	cn/com/fmsh/tsm/business/core/BusinessExtendImpl:a	Lcn/com/fmsh/util/log/FMLog;
    //   1094: ifnull +43 -> 1137
    //   1097: aload_0
    //   1098: getfield 19	cn/com/fmsh/tsm/business/core/BusinessExtendImpl:a	Lcn/com/fmsh/util/log/FMLog;
    //   1101: aload_0
    //   1102: getfield 29	cn/com/fmsh/tsm/business/core/BusinessExtendImpl:b	Ljava/lang/String;
    //   1105: new 71	java/lang/StringBuilder
    //   1108: dup
    //   1109: aload 5
    //   1111: invokestatic 77	java/lang/String:valueOf	(Ljava/lang/Object;)Ljava/lang/String;
    //   1114: invokespecial 80	java/lang/StringBuilder:<init>	(Ljava/lang/String;)V
    //   1117: iconst_4
    //   1118: bipush 98
    //   1120: ldc_w 479
    //   1123: invokestatic 88	cn/com/fmsh/FM_Exception:getChars	(IILjava/lang/String;)Ljava/lang/String;
    //   1126: invokevirtual 92	java/lang/StringBuilder:append	(Ljava/lang/String;)Ljava/lang/StringBuilder;
    //   1129: invokevirtual 95	java/lang/StringBuilder:toString	()Ljava/lang/String;
    //   1132: invokeinterface 98 3 0
    //   1137: new 45	cn/com/fmsh/tsm/business/exception/BusinessException
    //   1140: dup
    //   1141: new 71	java/lang/StringBuilder
    //   1144: dup
    //   1145: aload 5
    //   1147: invokestatic 77	java/lang/String:valueOf	(Ljava/lang/Object;)Ljava/lang/String;
    //   1150: invokespecial 80	java/lang/StringBuilder:<init>	(Ljava/lang/String;)V
    //   1153: bipush 78
    //   1155: ldc_w 481
    //   1158: invokestatic 137	cn/com/fmsh/util/CRCUtil:valueOf	(ILjava/lang/String;)Ljava/lang/String;
    //   1161: invokevirtual 92	java/lang/StringBuilder:append	(Ljava/lang/String;)Ljava/lang/StringBuilder;
    //   1164: invokevirtual 95	java/lang/StringBuilder:toString	()Ljava/lang/String;
    //   1167: getstatic 168	cn/com/fmsh/tsm/business/exception/BusinessException$ErrorMessage:local_app_query_server_fail	Lcn/com/fmsh/tsm/business/exception/BusinessException$ErrorMessage;
    //   1170: invokespecial 115	cn/com/fmsh/tsm/business/exception/BusinessException:<init>	(Ljava/lang/String;Lcn/com/fmsh/tsm/business/exception/BusinessException$ErrorMessage;)V
    //   1173: athrow
    //
    // Exception table:
    //   from	to	target	type
    //   548	684	237	cn/com/fmsh/communication/message/exception/FMCommunicationMessageException
    //   475	515	781	cn/com/fmsh/communication/message/exception/FMCommunicationMessageException
  }
}

/* Location:           d:\Users\Administrator\Desktop\111111_dex2jar.jar
 * Qualified Name:     cn.com.fmsh.tsm.business.core.BusinessExtendImpl
 * JD-Core Version:    0.6.0
 */